Workbook

Sheet plan de producción
Q1: lleno manual | R1: lleno manual | S1: lleno manual | U1: lleno manual | V1: lleno manual | Y1: lleno manual | AE1: lleno manual | AH1: AVANCE:
A2: PREVIOS | P2: LUNES | R2: MARTES | T2: MIERCOLES | U2: JUEVES | V2: VIERNES | Z2: Precio catálogo | AA2: Arrastrar | AB2: Arrastrar | AC2: Arrastrar | AH2: 1. Material | AI2: 2. ARMAR | AJ2: 3. Resoldar | AK2: 4. Pulir | AL2: 5. Pintar | AM2: 6. Ensamblar | AN2: 7. Empacar | AO2: Enviado
AA3: 0.3 | AD3: 0 | AF3: DIA A TERMINAR: | AH3: 20 | AI3: 40 | AJ3: 50 | AK3: 70 | AL3: 80 | AM3: 90 | AN3: 100
N4: Avance %: | O4: imp. | P4: Estado /sitio | Q4: COTI. | R4: CLIENTE | S4: Cod. equip. | T4: Equipo | U4: color | V4: CIUDAD | W4: LINEA | Y4: VENTA Antes de Iva | Z4: (ref. automática) | AA4: Horas max totales a invertir: | AB4: Horas faltantes x invertir: | AC4: dias hom faltantes x invertir: | AD4: Acum. a invertir | AE4: Quien: | AF4: Ofrecido: | AG4: Actualizado:
N5: 1 | P5: 1 | Q5: 3 | R5: JHON - NICOLAS | S5: XM161 | T5: Rack Sentadilla | U5: AZUL OSCURO | V5: Pereira | W5: musculación | Y5: 1990000 | Z5: =IFERROR(VLOOKUP(S5,'Precios y materiales '!$A:$C,3,FALSE),"") -> 1990000 | AA5: =(Y5*$AA$3)/'Mano de obra'!$C$9 -> 27.112241 | AB5: =AA5*(1-N5) -> 0 | AC5: =AB5/9 -> 0 | AD5: =AD3+(AA5*(1-N5)) -> 0 | AF5: 4 may | AG5: =IFERROR(TEXT(HLOOKUP(AD5,'Mano de obra'!$L$23:$BP$25,3,TRUE),"d mmm"),"") -> 27 May | AH5: =IF((($N5)*100)>='plan de producción'!AH$3,"x"," Material") -> x | AI5: =IF((($N5)*100)>='plan de producción'!AI$3,"x","Armar ") -> x | AJ5: =IF((($N5)*100)>='plan de producción'!AJ$3,"x"," Resoldar") -> x | AK5: =IF((($N5)*100)>='plan de producción'!AK$3,"x"," Pulir") -> x | AL5: =IF((($N5)*100)>='plan de producción'!AL$3,"x","Pintar ") -> x | AM5: =IF((($N5)*100)>='plan de producción'!AM$3,"x","Ensamblar ") -> x | AN5: =IF((($N5)*100)>='plan de producción'!AN$3,"x"," Empacar") -> x
M6: Cojines | N6: 1 | P6: 2 | Q6: 10 | R6: JHON - NICOLAS | S6: XM104 | T6: Banco hombro peso libre | U6: AZUL OSCURO | V6: Pereira | W6: musculación | Y6: 650000 | Z6: =IFERROR(VLOOKUP(S6,'Precios y materiales '!$A:$C,3,FALSE),"") -> 650000 | AA6: =(Y6*$AA$3)/'Mano de obra'!$C$9 -> 8.855757 | AB6: =AA6*(1-N6) -> 0 | AC6: =AB6/9 -> 0 | AD6: =AD5+(AA6*(1-N6)) -> 0 | AF6: 4 may | AG6: =IFERROR(TEXT(HLOOKUP(AD6,'Mano de obra'!$L$23:$BP$25,3,TRUE),"d mmm"),"") -> 27 May | AH6: =IF((($N6)*100)>='plan de producción'!AH$3,"x"," Material") -> x | AI6: =IF((($N6)*100)>='plan de producción'!AI$3,"x","Armar ") -> x | AJ6: =IF((($N6)*100)>='plan de producción'!AJ$3,"x"," Resoldar") -> x | AK6: =IF((($N6)*100)>='plan de producción'!AK$3,"x"," Pulir") -> x | AL6: =IF((($N6)*100)>='plan de producción'!AL$3,"x","Pintar ") -> x | AM6: =IF((($N6)*100)>='plan de producción'!AM$3,"x","Ensamblar ") -> x | AN6: =IF((($N6)*100)>='plan de producción'!AN$3,"x"," Empacar") -> x
M7: Cojines | N7: 1 | P7: 3 | Q7: 974 | R7: JHON - NICOLAS | S7: XM104 | T7: Banco hombro peso libre | U7: AZUL OSCURO | V7: Pereira | W7: musculación | Y7: 650000 | Z7: =IFERROR(VLOOKUP(S7,'Precios y materiales '!$A:$C,3,FALSE),"") -> 650000 | AA7: =(Y7*$AA$3)/'Mano de obra'!$C$9 -> 8.855757 | AB7: =AA7*(1-N7) -> 0 | AC7: =AB7/9 -> 0 | AD7: =AD6+(AA7*(1-N7)) -> 0 | AF7: 5 may | AG7: =IFERROR(TEXT(HLOOKUP(AD7,'Mano de obra'!$L$23:$BP$25,3,TRUE),"d mmm"),"") -> 27 May | AH7: =IF((($N7)*100)>='plan de producción'!AH$3,"x"," Material") -> x | AI7: =IF((($N7)*100)>='plan de producción'!AI$3,"x","Armar ") -> x | AJ7: =IF((($N7)*100)>='plan de producción'!AJ$3,"x"," Resoldar") -> x | AK7: =IF((($N7)*100)>='plan de producción'!AK$3,"x"," Pulir") -> x | AL7: =IF((($N7)*100)>='plan de producción'!AL$3,"x","Pintar ") -> x | AM7: =IF((($N7)*100)>='plan de producción'!AM$3,"x","Ensamblar ") -> x | AN7: =IF((($N7)*100)>='plan de producción'!AN$3,"x"," Empacar") -> x
M8: Cojines | N8: 1 | P8: 4 | Q8: 977 | R8: JHON - NICOLAS | S8: XM165 | T8: Sentadilla Bulgara | U8: AZUL OSCURO | V8: Pereira | W8: musculación | Y8: 490000 | Z8: =IFERROR(VLOOKUP(S8,'Precios y materiales '!$A:$C,3,FALSE),"") -> 490000 | AA8: =(Y8*$AA$3)/'Mano de obra'!$C$9 -> 6.6758783 | AB8: =AA8*(1-N8) -> 0 | AC8: =AB8/9 -> 0 | AD8: =AD7+(AA8*(1-N8)) -> 0 | AF8: 5 may | AG8: =IFERROR(TEXT(HLOOKUP(AD8,'Mano de obra'!$L$23:$BP$25,3,TRUE),"d mmm"),"") -> 27 May | AH8: =IF((($N8)*100)>='plan de producción'!AH$3,"x"," Material") -> x | AI8: =IF((($N8)*100)>='plan de producción'!AI$3,"x","Armar ") -> x | AJ8: =IF((($N8)*100)>='plan de producción'!AJ$3,"x"," Resoldar") -> x | AK8: =IF((($N8)*100)>='plan de producción'!AK$3,"x"," Pulir") -> x | AL8: =IF((($N8)*100)>='plan de producción'!AL$3,"x","Pintar ") -> x | AM8: =IF((($N8)*100)>='plan de producción'!AM$3,"x","Ensamblar ") -> x | AN8: =IF((($N8)*100)>='plan de producción'!AN$3,"x"," Empacar") -> x
M9: Cojines | N9: 0.9 | P9: 5 | Q9: 5 | R9: JHON - NICOLAS | S9: XM108 | T9: banco olimpico plano | U9: AZUL OSCURO | V9: Pereira | W9: musculación | Y9: 1490000 | Z9: =IFERROR(VLOOKUP(S9,'Precios y materiales '!$A:$C,3,FALSE),"") -> 1490000 | AA9: =(Y9*$AA$3)/'Mano de obra'!$C$9 -> 20.30012 | AB9: =AA9*(1-N9) -> 2.030012 | AC9: =AB9/9 -> 0.22555689 | AD9: =AD8+(AA9*(1-N9)) -> 2.030012 | AF9: 5 may | AG9: =IFERROR(TEXT(HLOOKUP(AD9,'Mano de obra'!$L$23:$BP$25,3,TRUE),"d mmm"),"") -> 27 May | AH9: =IF((($N9)*100)>='plan de producción'!AH$3,"x"," Material") -> x | AI9: =IF((($N9)*100)>='plan de producción'!AI$3,"x","Armar ") -> x | AJ9: =IF((($N9)*100)>='plan de producción'!AJ$3,"x"," Resoldar") -> x | AK9: =IF((($N9)*100)>='plan de producción'!AK$3,"x"," Pulir") -> x | AL9: =IF((($N9)*100)>='plan de producción'!AL$3,"x","Pintar ") -> x | AM9: =IF((($N9)*100)>='plan de producción'!AM$3,"x","Ensamblar ") -> x | AN9: =IF((($N9)*100)>='plan de producción'!AN$3,"x"," Empacar") -> Empacar
B10: Torno E. | M10: Cojines | N10: 1 | P10: 6 | Q10: 1 | R10: JHON - NICOLAS | S10: XM105 | T10: Banco Multifunción | U10: AZUL OSCURO | V10: Pereira | W10: musculación | Y10: 1190000 | Z10: =IFERROR(VLOOKUP(S10,'Precios y materiales '!$A:$C,3,FALSE),"") -> 1190000 | AA10: =(Y10*$AA$3)/'Mano de obra'!$C$9 -> 16.212847 | AB10: =AA10*(1-N10) -> 0 | AC10: =AB10/9 -> 0 | AD10: =AD9+(AA10*(1-N10)) -> 2.030012 | AF10: 5 may | AG10: =IFERROR(TEXT(HLOOKUP(AD10,'Mano de obra'!$L$23:$BP$25,3,TRUE),"d mmm"),"") -> 27 May | AH10: =IF((($N10)*100)>='plan de producción'!AH$3,"x"," Material") -> x | AI10: =IF((($N10)*100)>='plan de producción'!AI$3,"x","Armar ") -> x | AJ10: =IF((($N10)*100)>='plan de producción'!AJ$3,"x"," Resoldar") -> x | AK10: =IF((($N10)*100)>='plan de producción'!AK$3,"x"," Pulir") -> x | AL10: =IF((($N10)*100)>='plan de producción'!AL$3,"x","Pintar ") -> x | AM10: =IF((($N10)*100)>='plan de producción'!AM$3,"x","Ensamblar ") -> x | AN10: =IF((($N10)*100)>='plan de producción'!AN$3,"x"," Empacar") -> x
B11: Torno E. | M11: Cojines | N11: 1 | P11: 7 | Q11: 975 | R11: JHON - NICOLAS | S11: XM105 | T11: Banco Multifunción | U11: AZUL OSCURO | V11: Pereira | W11: musculación | Y11: 1190000 | Z11: =IFERROR(VLOOKUP(S11,'Precios y materiales '!$A:$C,3,FALSE),"") -> 1190000 | AA11: =(Y11*$AA$3)/'Mano de obra'!$C$9 -> 16.212847 | AB11: =AA11*(1-N11) -> 0 | AC11: =AB11/9 -> 0 | AD11: =AD10+(AA11*(1-N11)) -> 2.030012 | AF11: 5 may | AG11: =IFERROR(TEXT(HLOOKUP(AD11,'Mano de obra'!$L$23:$BP$25,3,TRUE),"d mmm"),"") -> 27 May | AH11: =IF((($N11)*100)>='plan de producción'!AH$3,"x"," Material") -> x | AI11: =IF((($N11)*100)>='plan de producción'!AI$3,"x","Armar ") -> x | AJ11: =IF((($N11)*100)>='plan de producción'!AJ$3,"x"," Resoldar") -> x | AK11: =IF((($N11)*100)>='plan de producción'!AK$3,"x"," Pulir") -> x | AL11: =IF((($N11)*100)>='plan de producción'!AL$3,"x","Pintar ") -> x | AM11: =IF((($N11)*100)>='plan de producción'!AM$3,"x","Ensamblar ") -> x | AN11: =IF((($N11)*100)>='plan de producción'!AN$3,"x"," Empacar") -> x
B12: Torno E. | M12: Cojines | N12: 1 | P12: 8 | Q12: 976 | R12: JHON - NICOLAS | S12: XM105 | T12: Banco Multifunción | U12: AZUL OSCURO | V12: Pereira | W12: musculación | Y12: 1190000 | Z12: =IFERROR(VLOOKUP(S12,'Precios y materiales '!$A:$C,3,FALSE),"") -> 1190000 | AA12: =(Y12*$AA$3)/'Mano de obra'!$C$9 -> 16.212847 | AB12: =AA12*(1-N12) -> 0 | AC12: =AB12/9 -> 0 | AD12: =AD11+(AA12*(1-N12)) -> 2.030012 | AF12: 6 may | AG12: =IFERROR(TEXT(HLOOKUP(AD12,'Mano de obra'!$L$23:$BP$25,3,TRUE),"d mmm"),"") -> 27 May | AH12: =IF((($N12)*100)>='plan de producción'!AH$3,"x"," Material") -> x | AI12: =IF((($N12)*100)>='plan de producción'!AI$3,"x","Armar ") -> x | AJ12: =IF((($N12)*100)>='plan de producción'!AJ$3,"x"," Resoldar") -> x | AK12: =IF((($N12)*100)>='plan de producción'!AK$3,"x"," Pulir") -> x | AL12: =IF((($N12)*100)>='plan de producción'!AL$3,"x","Pintar ") -> x | AM12: =IF((($N12)*100)>='plan de producción'!AM$3,"x","Ensamblar ") -> x | AN12: =IF((($N12)*100)>='plan de producción'!AN$3,"x"," Empacar") -> x
M13: Cojines | N13: 0.9 | P13: 9 | Q13: 13 | R13: JHON - NICOLAS | S13: XM111 | T13: Banco Predicador Libre | U13: AZUL OSCURO | V13: Pereira | W13: musculación | Y13: 1250000 | Z13: =IFERROR(VLOOKUP(S13,'Precios y materiales '!$A:$C,3,FALSE),"") -> 1250000 | AA13: =(Y13*$AA$3)/'Mano de obra'!$C$9 -> 17.030302 | AB13: =AA13*(1-N13) -> 1.7030302 | AC13: =AB13/9 -> 0.18922558 | AD13: =AD12+(AA13*(1-N13)) -> 3.7330422 | AF13: 6 may | AG13: =IFERROR(TEXT(HLOOKUP(AD13,'Mano de obra'!$L$23:$BP$25,3,TRUE),"d mmm"),"") -> 27 May | AH13: =IF((($N13)*100)>='plan de producción'!AH$3,"x"," Material") -> x | AI13: =IF((($N13)*100)>='plan de producción'!AI$3,"x","Armar ") -> x | AJ13: =IF((($N13)*100)>='plan de producción'!AJ$3,"x"," Resoldar") -> x | AK13: =IF((($N13)*100)>='plan de producción'!AK$3,"x"," Pulir") -> x | AL13: =IF((($N13)*100)>='plan de producción'!AL$3,"x","Pintar ") -> x | AM13: =IF((($N13)*100)>='plan de producción'!AM$3,"x","Ensamblar ") -> x | AN13: =IF((($N13)*100)>='plan de producción'!AN$3,"x"," Empacar") -> Empacar
B14: Torno E. | M14: Cojines | N14: 0.9 | P14: 10 | Q14: 12 | R14: JHON - NICOLAS | S14: XM130 | T14: Hammer remo | U14: AZUL OSCURO | V14: Pereira | W14: musculación | Y14: 2100000 | Z14: =IFERROR(VLOOKUP(S14,'Precios y materiales '!$A:$C,3,FALSE),"") -> 2100000 | AA14: =(Y14*$AA$3)/'Mano de obra'!$C$9 -> 28.610907 | AB14: =AA14*(1-N14) -> 2.8610907 | AC14: =AB14/9 -> 0.31789897 | AD14: =AD13+(AA14*(1-N14)) -> 6.5941329 | AF14: 6 may | AG14: =IFERROR(TEXT(HLOOKUP(AD14,'Mano de obra'!$L$23:$BP$25,3,TRUE),"d mmm"),"") -> 27 May | AH14: =IF((($N14)*100)>='plan de producción'!AH$3,"x"," Material") -> x | AI14: =IF((($N14)*100)>='plan de producción'!AI$3,"x","Armar ") -> x | AJ14: =IF((($N14)*100)>='plan de producción'!AJ$3,"x"," Resoldar") -> x | AK14: =IF((($N14)*100)>='plan de producción'!AK$3,"x"," Pulir") -> x | AL14: =IF((($N14)*100)>='plan de producción'!AL$3,"x","Pintar ") -> x | AM14: =IF((($N14)*100)>='plan de producción'!AM$3,"x","Ensamblar ") -> x | AN14: =IF((($N14)*100)>='plan de producción'!AN$3,"x"," Empacar") -> Empacar
B15: Torno E. | M15: Cojines | N15: 1 | P15: 11 | Q15: 42 | R15: JHON - NICOLAS | S15: XM162 | T15: Remo en punta | U15: AZUL OSCURO | V15: Pereira | W15: musculación | Y15: 1750000 | Z15: =IFERROR(VLOOKUP(S15,'Precios y materiales '!$A:$C,3,FALSE),"") -> 1750000 | AA15: =(Y15*$AA$3)/'Mano de obra'!$C$9 -> 23.842423 | AB15: =AA15*(1-N15) -> 0 | AC15: =AB15/9 -> 0 | AD15: =AD14+(AA15*(1-N15)) -> 6.5941329 | AF15: 7 may | AG15: =IFERROR(TEXT(HLOOKUP(AD15,'Mano de obra'!$L$23:$BP$25,3,TRUE),"d mmm"),"") -> 27 May | AH15: =IF((($N15)*100)>='plan de producción'!AH$3,"x"," Material") -> x | AI15: =IF((($N15)*100)>='plan de producción'!AI$3,"x","Armar ") -> x | AJ15: =IF((($N15)*100)>='plan de producción'!AJ$3,"x"," Resoldar") -> x | AK15: =IF((($N15)*100)>='plan de producción'!AK$3,"x"," Pulir") -> x | AL15: =IF((($N15)*100)>='plan de producción'!AL$3,"x","Pintar ") -> x | AM15: =IF((($N15)*100)>='plan de producción'!AM$3,"x","Ensamblar ") -> x | AN15: =IF((($N15)*100)>='plan de producción'!AN$3,"x"," Empacar") -> x
B16: Torno E. | M16: Cojines | N16: 1 | P16: 12 | Q16: 32 | R16: JHON - NICOLAS | S16: XM140 | T16: Pantorrillero | U16: AZUL OSCURO | V16: Pereira | W16: musculación | Y16: 1390000 | Z16: =IFERROR(VLOOKUP(S16,'Precios y materiales '!$A:$C,3,FALSE),"") -> 1390000 | AA16: =(Y16*$AA$3)/'Mano de obra'!$C$9 -> 18.937696 | AB16: =AA16*(1-N16) -> 0 | AC16: =AB16/9 -> 0 | AD16: =AD15+(AA16*(1-N16)) -> 6.5941329 | AF16: 7 may | AG16: =IFERROR(TEXT(HLOOKUP(AD16,'Mano de obra'!$L$23:$BP$25,3,TRUE),"d mmm"),"") -> 27 May | AH16: =IF((($N16)*100)>='plan de producción'!AH$3,"x"," Material") -> x | AI16: =IF((($N16)*100)>='plan de producción'!AI$3,"x","Armar ") -> x | AJ16: =IF((($N16)*100)>='plan de producción'!AJ$3,"x"," Resoldar") -> x | AK16: =IF((($N16)*100)>='plan de producción'!AK$3,"x"," Pulir") -> x | AL16: =IF((($N16)*100)>='plan de producción'!AL$3,"x","Pintar ") -> x | AM16: =IF((($N16)*100)>='plan de producción'!AM$3,"x","Ensamblar ") -> x | AN16: =IF((($N16)*100)>='plan de producción'!AN$3,"x"," Empacar") -> x
B17: Torno E. | M17: Cojines | N17: 0.7 | P17: 13 | Q17: 2 | R17: JHON - NICOLAS | S17: XM184 | T17: Prensa Atletica 3.0 lineal | U17: AZUL OSCURO | V17: Pereira | W17: musculación | Y17: 3990000 | Z17: =IFERROR(VLOOKUP(S17,'Precios y materiales '!$A:$C,3,FALSE),"") -> 3990000 | AA17: =(Y17*$AA$3)/'Mano de obra'!$C$9 -> 54.360723 | AB17: =AA17*(1-N17) -> 16.308217 | AC17: =AB17/9 -> 1.8120241 | AD17: =AD16+(AA17*(1-N17)) -> 22.90235 | AF17: 10 may | AG17: =IFERROR(TEXT(HLOOKUP(AD17,'Mano de obra'!$L$23:$BP$25,3,TRUE),"d mmm"),"") -> 27 May | AH17: =IF((($N17)*100)>='plan de producción'!AH$3,"x"," Material") -> x | AI17: =IF((($N17)*100)>='plan de producción'!AI$3,"x","Armar ") -> x | AJ17: =IF((($N17)*100)>='plan de producción'!AJ$3,"x"," Resoldar") -> x | AK17: =IF((($N17)*100)>='plan de producción'!AK$3,"x"," Pulir") -> x | AL17: =IF((($N17)*100)>='plan de producción'!AL$3,"x","Pintar ") -> Pintar | AM17: =IF((($N17)*100)>='plan de producción'!AM$3,"x","Ensamblar ") -> Ensamblar | AN17: =IF((($N17)*100)>='plan de producción'!AN$3,"x"," Empacar") -> Empacar
B18: Torno E. | M18: Cojines | N18: 0.9 | P18: 14 | Q18: 4 | R18: JHON - NICOLAS | S18: XM100 | T18: Abductor Aductor | U18: AZUL OSCURO | V18: Pereira | W18: musculación | Y18: 4000000 | Z18: =IFERROR(VLOOKUP(S18,'Precios y materiales '!$A:$C,3,FALSE),"") -> 4000000 | AA18: =(Y18*$AA$3)/'Mano de obra'!$C$9 -> 54.496966 | AB18: =AA18*(1-N18) -> 5.4496966 | AC18: =AB18/9 -> 0.60552184 | AD18: =AD17+(AA18*(1-N18)) -> 28.352047 | AF18: 10 may | AG18: =IFERROR(TEXT(HLOOKUP(AD18,'Mano de obra'!$L$23:$BP$25,3,TRUE),"d mmm"),"") -> 27 May | AH18: =IF((($N18)*100)>='plan de producción'!AH$3,"x"," Material") -> x | AI18: =IF((($N18)*100)>='plan de producción'!AI$3,"x","Armar ") -> x | AJ18: =IF((($N18)*100)>='plan de producción'!AJ$3,"x"," Resoldar") -> x | AK18: =IF((($N18)*100)>='plan de producción'!AK$3,"x"," Pulir") -> x | AL18: =IF((($N18)*100)>='plan de producción'!AL$3,"x","Pintar ") -> x | AM18: =IF((($N18)*100)>='plan de producción'!AM$3,"x","Ensamblar ") -> x | AN18: =IF((($N18)*100)>='plan de producción'!AN$3,"x"," Empacar") -> Empacar
N19: 0.5 | P19: 15 | Q19: 978 | R19: JHON - NICOLAS | S19: XC103 | T19: PIVOTE DE BARRA PARA JAULA | U19: AZUL OSCURO | V19: Pereira | W19: musculación | Y19: 168067.23 | Z19: =IFERROR(VLOOKUP(S19,'Precios y materiales '!$A:$C,3,FALSE),"") | AA19: =(Y19*$AA$3)/'Mano de obra'!$C$9 -> 2.2897885 | AB19: =AA19*(1-N19) -> 1.1448942 | AC19: =AB19/9 -> 0.12721047 | AD19: =AD18+(AA19*(1-N19)) -> 29.496941 | AF19: 10 may | AG19: =IFERROR(TEXT(HLOOKUP(AD19,'Mano de obra'!$L$23:$BP$25,3,TRUE),"d mmm"),"") -> 27 May | AH19: =IF((($N19)*100)>='plan de producción'!AH$3,"x"," Material") -> x | AI19: =IF((($N19)*100)>='plan de producción'!AI$3,"x","Armar ") -> x | AJ19: =IF((($N19)*100)>='plan de producción'!AJ$3,"x"," Resoldar") -> x | AK19: =IF((($N19)*100)>='plan de producción'!AK$3,"x"," Pulir") -> Pulir | AL19: =IF((($N19)*100)>='plan de producción'!AL$3,"x","Pintar ") -> Pintar | AM19: =IF((($N19)*100)>='plan de producción'!AM$3,"x","Ensamblar ") -> Ensamblar | AN19: =IF((($N19)*100)>='plan de producción'!AN$3,"x"," Empacar") -> Empacar
A20: Torno A. | N20: 0.2 | P20: 16 | Q20: 979 | R20: JHON - NICOLAS | S20: XC101 | T20: Accesorio fondos para jaula | U20: AZUL OSCURO | V20: Pereira | W20: musculación | Y20: 136974.79 | Z20: =IFERROR(VLOOKUP(S20,'Precios y materiales '!$A:$C,3,FALSE),"") | AA20: =(Y20*$AA$3)/'Mano de obra'!$C$9 -> 1.8661776 | AB20: =AA20*(1-N20) -> 1.4929421 | AC20: =AB20/9 -> 0.16588245 | AD20: =AD19+(AA20*(1-N20)) -> 30.989883 | AF20: 12 may | AG20: =IFERROR(TEXT(HLOOKUP(AD20,'Mano de obra'!$L$23:$BP$25,3,TRUE),"d mmm"),"") -> 27 May | AH20: =IF((($N20)*100)>='plan de producción'!AH$3,"x"," Material") -> x | AI20: =IF((($N20)*100)>='plan de producción'!AI$3,"x","Armar ") -> Armar | AJ20: =IF((($N20)*100)>='plan de producción'!AJ$3,"x"," Resoldar") -> Resoldar | AK20: =IF((($N20)*100)>='plan de producción'!AK$3,"x"," Pulir") -> Pulir | AL20: =IF((($N20)*100)>='plan de producción'!AL$3,"x","Pintar ") -> Pintar | AM20: =IF((($N20)*100)>='plan de producción'!AM$3,"x","Ensamblar ") -> Ensamblar | AN20: =IF((($N20)*100)>='plan de producción'!AN$3,"x"," Empacar") -> Empacar
A21: Torno A. | B21: Torno E. | M21: Cojines | N21: 0.2 | P21: 17 | Q21: 980 | R21: JHON - NICOLAS | S21: XM181 | T21: Jaula de Potencia para peso | U21: AZUL OSCURO | V21: Pereira | W21: musculación | Y21: 2880000 | Z21: =IFERROR(VLOOKUP(S21,'Precios y materiales '!$A:$C,3,FALSE),"") -> 2880000 | AA21: =(Y21*$AA$3)/'Mano de obra'!$C$9 -> 39.237815 | AB21: =AA21*(1-N21) -> 31.390252 | AC21: =AB21/9 -> 3.4878058 | AD21: =AD20+(AA21*(1-N21)) -> 62.380135 | AF21: 12 may | AG21: =IFERROR(TEXT(HLOOKUP(AD21,'Mano de obra'!$L$23:$BP$25,3,TRUE),"d mmm"),"") -> 27 May | AH21: =IF((($N21)*100)>='plan de producción'!AH$3,"x"," Material") -> x | AI21: =IF((($N21)*100)>='plan de producción'!AI$3,"x","Armar ") -> Armar | AJ21: =IF((($N21)*100)>='plan de producción'!AJ$3,"x"," Resoldar") -> Resoldar | AK21: =IF((($N21)*100)>='plan de producción'!AK$3,"x"," Pulir") -> Pulir | AL21: =IF((($N21)*100)>='plan de producción'!AL$3,"x","Pintar ") -> Pintar | AM21: =IF((($N21)*100)>='plan de producción'!AM$3,"x","Ensamblar ") -> Ensamblar | AN21: =IF((($N21)*100)>='plan de producción'!AN$3,"x"," Empacar") -> Empacar
A22: Torno A. | B22: Torno E. | M22: Cojines | N22: 0.8 | P22: 18 | Q22: 17 | R22: JHON - NICOLAS | S22: XM148 | T22: Polea Alta | U22: AZUL OSCURO | V22: Pereira | W22: musculación | Y22: 3890000 | Z22: =IFERROR(VLOOKUP(S22,'Precios y materiales '!$A:$C,3,FALSE),"") -> 3890000 | AA22: =(Y22*$AA$3)/'Mano de obra'!$C$9 -> 52.998299 | AB22: =AA22*(1-N22) -> 10.59966 | AC22: =AB22/9 -> 1.17774 | AD22: =AD21+(AA22*(1-N22)) -> 72.979795 | AF22: 13 may | AG22: =IFERROR(TEXT(HLOOKUP(AD22,'Mano de obra'!$L$23:$BP$25,3,TRUE),"d mmm"),"") -> 28 May | AH22: =IF((($N22)*100)>='plan de producción'!AH$3,"x"," Material") -> x | AI22: =IF((($N22)*100)>='plan de producción'!AI$3,"x","Armar ") -> x | AJ22: =IF((($N22)*100)>='plan de producción'!AJ$3,"x"," Resoldar") -> x | AK22: =IF((($N22)*100)>='plan de producción'!AK$3,"x"," Pulir") -> x | AL22: =IF((($N22)*100)>='plan de producción'!AL$3,"x","Pintar ") -> x | AM22: =IF((($N22)*100)>='plan de producción'!AM$3,"x","Ensamblar ") -> Ensamblar | AN22: =IF((($N22)*100)>='plan de producción'!AN$3,"x"," Empacar") -> Empacar
B23: Torno E. | M23: Cojines | N23: 0.2 | P23: 19 | Q23: 981 | R23: JHON - NICOLAS | S23: XM185 | T23: Sentadilla Hack Up 3.0 Lineal | U23: AZUL OSCURO | V23: Pereira | W23: musculación | Y23: 3990000 | Z23: =IFERROR(VLOOKUP(S23,'Precios y materiales '!$A:$C,3,FALSE),"") -> 3990000 | AA23: =(Y23*$AA$3)/'Mano de obra'!$C$9 -> 54.360723 | AB23: =AA23*(1-N23) -> 43.488579 | AC23: =AB23/9 -> 4.8320643 | AD23: =AD22+(AA23*(1-N23)) -> 116.46837 | AF23: 14 may | AG23: =IFERROR(TEXT(HLOOKUP(AD23,'Mano de obra'!$L$23:$BP$25,3,TRUE),"d mmm"),"") -> 28 May | AH23: =IF((($N23)*100)>='plan de producción'!AH$3,"x"," Material") -> x | AI23: =IF((($N23)*100)>='plan de producción'!AI$3,"x","Armar ") -> Armar | AJ23: =IF((($N23)*100)>='plan de producción'!AJ$3,"x"," Resoldar") -> Resoldar | AK23: =IF((($N23)*100)>='plan de producción'!AK$3,"x"," Pulir") -> Pulir | AL23: =IF((($N23)*100)>='plan de producción'!AL$3,"x","Pintar ") -> Pintar | AM23: =IF((($N23)*100)>='plan de producción'!AM$3,"x","Ensamblar ") -> Ensamblar | AN23: =IF((($N23)*100)>='plan de producción'!AN$3,"x"," Empacar") -> Empacar
A24: Torno A. | B24: Torno E. | N24: 0.9 | P24: 20 | Q24: 28 | R24: JHON - NICOLAS | S24: XM113 | T24: Crossover clásica | U24: AZUL OSCURO | V24: Pereira | W24: musculación | Y24: 5600000 | Z24: =IFERROR(VLOOKUP(S24,'Precios y materiales '!$A:$C,3,FALSE),"") -> 5600000 | AA24: =(Y24*$AA$3)/'Mano de obra'!$C$9 -> 76.295752 | AB24: =AA24*(1-N24) -> 7.6295752 | AC24: =AB24/9 -> 0.84773058 | AD24: =AD23+(AA24*(1-N24)) -> 124.09795 | AF24: 15 may | AG24: =IFERROR(TEXT(HLOOKUP(AD24,'Mano de obra'!$L$23:$BP$25,3,TRUE),"d mmm"),"") -> 31 May | AH24: =IF((($N24)*100)>='plan de producción'!AH$3,"x"," Material") -> x | AI24: =IF((($N24)*100)>='plan de producción'!AI$3,"x","Armar ") -> x | AJ24: =IF((($N24)*100)>='plan de producción'!AJ$3,"x"," Resoldar") -> x | AK24: =IF((($N24)*100)>='plan de producción'!AK$3,"x"," Pulir") -> x | AL24: =IF((($N24)*100)>='plan de producción'!AL$3,"x","Pintar ") -> x | AM24: =IF((($N24)*100)>='plan de producción'!AM$3,"x","Ensamblar ") -> x | AN24: =IF((($N24)*100)>='plan de producción'!AN$3,"x"," Empacar") -> Empacar
A25: Torno A. | B25: Torno E. | M25: Cojines | N25: 0.8 | P25: 21 | Q25: 16 | R25: JHON - NICOLAS | S25: XM145 | T25: Peck Deck doble función | U25: AZUL OSCURO | V25: Pereira | W25: musculación | Y25: 3990000 | Z25: =IFERROR(VLOOKUP(S25,'Precios y materiales '!$A:$C,3,FALSE),"") -> 3990000 | AA25: =(Y25*$AA$3)/'Mano de obra'!$C$9 -> 54.360723 | AB25: =AA25*(1-N25) -> 10.872145 | AC25: =AB25/9 -> 1.2080161 | AD25: =AD24+(AA25*(1-N25)) -> 134.97009 | AF25: 18 may | AG25: =IFERROR(TEXT(HLOOKUP(AD25,'Mano de obra'!$L$23:$BP$25,3,TRUE),"d mmm"),"") -> 31 May | AH25: =IF((($N25)*100)>='plan de producción'!AH$3,"x"," Material") -> x | AI25: =IF((($N25)*100)>='plan de producción'!AI$3,"x","Armar ") -> x | AJ25: =IF((($N25)*100)>='plan de producción'!AJ$3,"x"," Resoldar") -> x | AK25: =IF((($N25)*100)>='plan de producción'!AK$3,"x"," Pulir") -> x | AL25: =IF((($N25)*100)>='plan de producción'!AL$3,"x","Pintar ") -> x | AM25: =IF((($N25)*100)>='plan de producción'!AM$3,"x","Ensamblar ") -> Ensamblar | AN25: =IF((($N25)*100)>='plan de producción'!AN$3,"x"," Empacar") -> Empacar
N26: 1 | P26: 22 | Q26: 982 | R26: JHON - NICOLAS | S26: XM908 | T26: rack mancuernas 2 niveles | U26: AZUL OSCURO | V26: Pereira | W26: musculación | Y26: 500000 | Z26: =IFERROR(VLOOKUP(S26,'Precios y materiales '!$A:$C,3,FALSE),"") -> 600000 | AA26: =(Y26*$AA$3)/'Mano de obra'!$C$9 -> 6.8121207 | AB26: =AA26*(1-N26) -> 0 | AC26: =AB26/9 -> 0 | AD26: =AD25+(AA26*(1-N26)) -> 134.97009 | AF26: 18 may | AG26: =IFERROR(TEXT(HLOOKUP(AD26,'Mano de obra'!$L$23:$BP$25,3,TRUE),"d mmm"),"") -> 31 May | AH26: =IF((($N26)*100)>='plan de producción'!AH$3,"x"," Material") -> x | AI26: =IF((($N26)*100)>='plan de producción'!AI$3,"x","Armar ") -> x | AJ26: =IF((($N26)*100)>='plan de producción'!AJ$3,"x"," Resoldar") -> x | AK26: =IF((($N26)*100)>='plan de producción'!AK$3,"x"," Pulir") -> x | AL26: =IF((($N26)*100)>='plan de producción'!AL$3,"x","Pintar ") -> x | AM26: =IF((($N26)*100)>='plan de producción'!AM$3,"x","Ensamblar ") -> x | AN26: =IF((($N26)*100)>='plan de producción'!AN$3,"x"," Empacar") -> x
N27: 1 | P27: 23 | Q27: 983 | R27: JHON - NICOLAS | S27: XM908 | T27: rack mancuernas 2 niveles | U27: AZUL OSCURO | V27: Pereira | W27: musculación | Y27: 500000 | Z27: =IFERROR(VLOOKUP(S27,'Precios y materiales '!$A:$C,3,FALSE),"") -> 600000 | AA27: =(Y27*$AA$3)/'Mano de obra'!$C$9 -> 6.8121207 | AB27: =AA27*(1-N27) -> 0 | AC27: =AB27/9 -> 0 | AD27: =AD26+(AA27*(1-N27)) -> 134.97009 | AF27: 18 may | AG27: =IFERROR(TEXT(HLOOKUP(AD27,'Mano de obra'!$L$23:$BP$25,3,TRUE),"d mmm"),"") -> 31 May | AH27: =IF((($N27)*100)>='plan de producción'!AH$3,"x"," Material") -> x | AI27: =IF((($N27)*100)>='plan de producción'!AI$3,"x","Armar ") -> x | AJ27: =IF((($N27)*100)>='plan de producción'!AJ$3,"x"," Resoldar") -> x | AK27: =IF((($N27)*100)>='plan de producción'!AK$3,"x"," Pulir") -> x | AL27: =IF((($N27)*100)>='plan de producción'!AL$3,"x","Pintar ") -> x | AM27: =IF((($N27)*100)>='plan de producción'!AM$3,"x","Ensamblar ") -> x | AN27: =IF((($N27)*100)>='plan de producción'!AN$3,"x"," Empacar") -> x
C28: Laser | N28: 1 | P28: 24 | Q28: 984 | R28: JHON - NICOLAS | S28: XM908 | T28: rack mancuernas 2 niveles | U28: AZUL OSCURO | V28: Pereira | W28: musculación | Y28: 764000 | Z28: =IFERROR(VLOOKUP(S28,'Precios y materiales '!$A:$C,3,FALSE),"") -> 600000 | AA28: =(Y28*$AA$3)/'Mano de obra'!$C$9 -> 10.40892 | AB28: =AA28*(1-N28) -> 0 | AC28: =AB28/9 -> 0 | AD28: =AD27+(AA28*(1-N28)) -> 134.97009 | AF28: 18 may | AG28: =IFERROR(TEXT(HLOOKUP(AD28,'Mano de obra'!$L$23:$BP$25,3,TRUE),"d mmm"),"") -> 31 May | AH28: =IF((($N28)*100)>='plan de producción'!AH$3,"x"," Material") -> x | AI28: =IF((($N28)*100)>='plan de producción'!AI$3,"x","Armar ") -> x | AJ28: =IF((($N28)*100)>='plan de producción'!AJ$3,"x"," Resoldar") -> x | AK28: =IF((($N28)*100)>='plan de producción'!AK$3,"x"," Pulir") -> x | AL28: =IF((($N28)*100)>='plan de producción'!AL$3,"x","Pintar ") -> x | AM28: =IF((($N28)*100)>='plan de producción'!AM$3,"x","Ensamblar ") -> x | AN28: =IF((($N28)*100)>='plan de producción'!AN$3,"x"," Empacar") -> x
A29: Torno A. | B29: Torno E. | M29: Cojines | N29: 0.2 | P29: 25 | Q29: 8 | R29: JHON - NICOLAS | S29: XM121 | T29: Flexor | U29: AZUL OSCURO | V29: Pereira | W29: musculación | Y29: 3600000 | Z29: =IFERROR(VLOOKUP(S29,'Precios y materiales '!$A:$C,3,FALSE),"") -> 3600000 | AA29: =(Y29*$AA$3)/'Mano de obra'!$C$9 -> 49.047269 | AB29: =AA29*(1-N29) -> 39.237815 | AC29: =AB29/9 -> 4.3597573 | AD29: =AD28+(AA29*(1-N29)) -> 174.20791 | AF29: 19 may | AG29: =IFERROR(TEXT(HLOOKUP(AD29,'Mano de obra'!$L$23:$BP$25,3,TRUE),"d mmm"),"") -> 31 May | AH29: =IF((($N29)*100)>='plan de producción'!AH$3,"x"," Material") -> x | AI29: =IF((($N29)*100)>='plan de producción'!AI$3,"x","Armar ") -> Armar | AJ29: =IF((($N29)*100)>='plan de producción'!AJ$3,"x"," Resoldar") -> Resoldar | AK29: =IF((($N29)*100)>='plan de producción'!AK$3,"x"," Pulir") -> Pulir | AL29: =IF((($N29)*100)>='plan de producción'!AL$3,"x","Pintar ") -> Pintar | AM29: =IF((($N29)*100)>='plan de producción'!AM$3,"x","Ensamblar ") -> Ensamblar | AN29: =IF((($N29)*100)>='plan de producción'!AN$3,"x"," Empacar") -> Empacar
A30: Torno A. | B30: Torno E. | M30: Cojines | N30: 0.2 | P30: 26 | Q30: 7 | R30: JHON - NICOLAS | S30: XM120 | T30: Flexo Extensor | U30: AZUL OSCURO | V30: Pereira | W30: musculación | Y30: 3990000 | Z30: =IFERROR(VLOOKUP(S30,'Precios y materiales '!$A:$C,3,FALSE),"") -> 3990000 | AA30: =(Y30*$AA$3)/'Mano de obra'!$C$9 -> 54.360723 | AB30: =AA30*(1-N30) -> 43.488579 | AC30: =AB30/9 -> 4.8320643 | AD30: =AD29+(AA30*(1-N30)) -> 217.69649 | AF30: 19 may | AG30: =IFERROR(TEXT(HLOOKUP(AD30,'Mano de obra'!$L$23:$BP$25,3,TRUE),"d mmm"),"") -> 1 Jun | AH30: =IF((($N30)*100)>='plan de producción'!AH$3,"x"," Material") -> x | AI30: =IF((($N30)*100)>='plan de producción'!AI$3,"x","Armar ") -> Armar | AJ30: =IF((($N30)*100)>='plan de producción'!AJ$3,"x"," Resoldar") -> Resoldar | AK30: =IF((($N30)*100)>='plan de producción'!AK$3,"x"," Pulir") -> Pulir | AL30: =IF((($N30)*100)>='plan de producción'!AL$3,"x","Pintar ") -> Pintar | AM30: =IF((($N30)*100)>='plan de producción'!AM$3,"x","Ensamblar ") -> Ensamblar | AN30: =IF((($N30)*100)>='plan de producción'!AN$3,"x"," Empacar") -> Empacar
A31: Torno A. | B31: Torno E. | I31: Zinc | N31: 0.2 | P31: 27 | Q31: 9 | R31: JHON - NICOLAS | S31: XM170 | T31: Sentadilla Smith 2.0 | U31: AZUL OSCURO | V31: Pereira | W31: musculación | Y31: 4450000 | Z31: =IFERROR(VLOOKUP(S31,'Precios y materiales '!$A:$C,3,FALSE),"") -> 4450000 | AA31: =(Y31*$AA$3)/'Mano de obra'!$C$9 -> 60.627875 | AB31: =AA31*(1-N31) -> 48.5023 | AC31: =AB31/9 -> 5.3891444 | AD31: =AD30+(AA31*(1-N31)) -> 266.19879 | AF31: 46162 | AG31: =IFERROR(TEXT(HLOOKUP(AD31,'Mano de obra'!$L$23:$BP$25,3,TRUE),"d mmm"),"") -> 2 Jun | AH31: =IF((($N31)*100)>='plan de producción'!AH$3,"x"," Material") -> x | AI31: =IF((($N31)*100)>='plan de producción'!AI$3,"x","Armar ") -> Armar | AJ31: =IF((($N31)*100)>='plan de producción'!AJ$3,"x"," Resoldar") -> Resoldar | AK31: =IF((($N31)*100)>='plan de producción'!AK$3,"x"," Pulir") -> Pulir | AL31: =IF((($N31)*100)>='plan de producción'!AL$3,"x","Pintar ") -> Pintar | AM31: =IF((($N31)*100)>='plan de producción'!AM$3,"x","Ensamblar ") -> Ensamblar | AN31: =IF((($N31)*100)>='plan de producción'!AN$3,"x"," Empacar") -> Empacar
A32: Torno A. | B32: Torno E. | C32: Laser | I32: Zinc | M32: Cojines | N32: 0 | P32: 28 | Q32: 29 | R32: JHON - NICOLAS | S32: XM116 | T32: Elevador de pelvis | U32: AZUL OSCURO | V32: Pereira | W32: musculación | Y32: 2490000 | Z32: =IFERROR(VLOOKUP(S32,'Precios y materiales '!$A:$C,3,FALSE),"") -> 2490000 | AA32: =(Y32*$AA$3)/'Mano de obra'!$C$9 -> 33.924361 | AB32: =AA32*(1-N32) -> 33.924361 | AC32: =AB32/9 -> 3.7693735 | AD32: =AD31+(AA32*(1-N32)) -> 300.12315 | AF32: 46162 | AG32: =IFERROR(TEXT(HLOOKUP(AD32,'Mano de obra'!$L$23:$BP$25,3,TRUE),"d mmm"),"") -> 2 Jun | AH32: =IF((($N32)*100)>='plan de producción'!AH$3,"x"," Material") -> Material | AI32: =IF((($N32)*100)>='plan de producción'!AI$3,"x","Armar ") -> Armar | AJ32: =IF((($N32)*100)>='plan de producción'!AJ$3,"x"," Resoldar") -> Resoldar | AK32: =IF((($N32)*100)>='plan de producción'!AK$3,"x"," Pulir") -> Pulir | AL32: =IF((($N32)*100)>='plan de producción'!AL$3,"x","Pintar ") -> Pintar | AM32: =IF((($N32)*100)>='plan de producción'!AM$3,"x","Ensamblar ") -> Ensamblar | AN32: =IF((($N32)*100)>='plan de producción'!AN$3,"x"," Empacar") -> Empacar
A33: Torno A. | B33: Torno E. | C33: Laser | D33: Carenaje | F33: Tubos | M33: Cojines | N33: 0.4 | Q33: 985 | R33: Diosivan Paez | S33: XM129 | T33: Hammer pecho plano | U33: MORADO NEGRO | V33: Ocaña | W33: Musculación | Y33: 2520000 | Z33: =IFERROR(VLOOKUP(S33,'Precios y materiales '!$A:$C,3,FALSE),"") -> 2520000 | AA33: =(Y33*$AA$3)/'Mano de obra'!$C$9 -> 34.333089 | AB33: =AA33*(1-N33) -> 20.599853 | AC33: =AB33/9 -> 2.2888726 | AD33: =AD32+(AA33*(1-N33)) -> 320.723 | AF33: 25 may | AG33: =IFERROR(TEXT(HLOOKUP(AD33,'Mano de obra'!$L$23:$BP$25,3,TRUE),"d mmm"),"") -> 2 Jun | AH33: =IF((($N33)*100)>='plan de producción'!AH$3,"x"," Material") -> x | AI33: =IF((($N33)*100)>='plan de producción'!AI$3,"x","Armar ") -> x | AJ33: =IF((($N33)*100)>='plan de producción'!AJ$3,"x"," Resoldar") -> Resoldar | AK33: =IF((($N33)*100)>='plan de producción'!AK$3,"x"," Pulir") -> Pulir | AL33: =IF((($N33)*100)>='plan de producción'!AL$3,"x","Pintar ") -> Pintar | AM33: =IF((($N33)*100)>='plan de producción'!AM$3,"x","Ensamblar ") -> Ensamblar | AN33: =IF((($N33)*100)>='plan de producción'!AN$3,"x"," Empacar") -> Empacar
B34: Torno E. | C34: Laser | D34: Carenaje | F34: Tubos | M34: Cojines | N34: 0.8 | Q34: 986 | R34: Diosivan Paez | S34: XM105 | T34: Banco Multifunción | U34: MORADO NEGRO | V34: Ocaña | W34: Musculación | Y34: 1190000 | Z34: =IFERROR(VLOOKUP(S34,'Precios y materiales '!$A:$C,3,FALSE),"") -> 1190000 | AA34: =(Y34*$AA$3)/'Mano de obra'!$C$9 -> 16.212847 | AB34: =AA34*(1-N34) -> 3.2425695 | AC34: =AB34/9 -> 0.3602855 | AD34: =AD33+(AA34*(1-N34)) -> 323.96557 | AF34: 25 may | AG34: =IFERROR(TEXT(HLOOKUP(AD34,'Mano de obra'!$L$23:$BP$25,3,TRUE),"d mmm"),"") -> 2 Jun | AH34: =IF((($N34)*100)>='plan de producción'!AH$3,"x"," Material") -> x | AI34: =IF((($N34)*100)>='plan de producción'!AI$3,"x","Armar ") -> x | AJ34: =IF((($N34)*100)>='plan de producción'!AJ$3,"x"," Resoldar") -> x | AK34: =IF((($N34)*100)>='plan de producción'!AK$3,"x"," Pulir") -> x | AL34: =IF((($N34)*100)>='plan de producción'!AL$3,"x","Pintar ") -> x | AM34: =IF((($N34)*100)>='plan de producción'!AM$3,"x","Ensamblar ") -> Ensamblar | AN34: =IF((($N34)*100)>='plan de producción'!AN$3,"x"," Empacar") -> Empacar
A35: Torno A. | B35: Torno E. | C35: Laser | D35: Carenaje | E35: Placas | F35: Tubos | G35: Inox. | H35: Pintu. | I35: Zinc | J35: Tornillos | K35: Rodam. | M35: Cojines | N35: 0.8 | Q35: 987 | R35: Camilo Aristizabal | S35: XB457 | T35: Pasamanos para parque | U35: negro…parece | V35: Manizales | W35: Bioparques | Y35: 2680000 | Z35: =IFERROR(VLOOKUP(S35,'Precios y materiales '!$A:$C,3,FALSE),"") -> 2680000 | AA35: =(Y35*$AA$3)/'Mano de obra'!$C$9 -> 36.512967 | AB35: =AA35*(1-N35) -> 7.3025934 | AC35: =AB35/9 -> 0.81139927 | AD35: =AD34+(AA35*(1-N35)) -> 331.26816 | AF35: 25 may | AG35: =IFERROR(TEXT(HLOOKUP(AD35,'Mano de obra'!$L$23:$BP$25,3,TRUE),"d mmm"),"") -> 2 Jun | AH35: =IF((($N35)*100)>='plan de producción'!AH$3,"x"," Material") -> x | AI35: =IF((($N35)*100)>='plan de producción'!AI$3,"x","Armar ") -> x | AJ35: =IF((($N35)*100)>='plan de producción'!AJ$3,"x"," Resoldar") -> x | AK35: =IF((($N35)*100)>='plan de producción'!AK$3,"x"," Pulir") -> x | AL35: =IF((($N35)*100)>='plan de producción'!AL$3,"x","Pintar ") -> x | AM35: =IF((($N35)*100)>='plan de producción'!AM$3,"x","Ensamblar ") -> Ensamblar | AN35: =IF((($N35)*100)>='plan de producción'!AN$3,"x"," Empacar") -> Empacar
A36: Torno A. | B36: Torno E. | C36: Laser | D36: Carenaje | E36: Placas | F36: Tubos | G36: Inox. | H36: Pintu. | I36: Zinc | J36: Tornillos | K36: Rodam. | N36: 0 | Q36: 988 | R36: PETRA proyectos y construcciones | S36: xb449 | T36: =VLOOKUP(S36,'Precios y materiales '!$A$2:$B$147,2,FALSE) -> Halon de espalda con discos | U36: naraja | V36: Pereira | W36: Bioparques | Y36: 16809075 | Z36: =IFERROR(VLOOKUP(S36,'Precios y materiales '!$A:$C,3,FALSE),"") -> 3151260.5 | AA36: =(Y36*$AA$3)/'Mano de obra'!$C$9 -> 229.0109 | AB36: =AA36*(1-N36) -> 229.0109 | AC36: =AB36/9 -> 25.445655 | AD36: =AD35+(AA36*(1-N36)) -> 560.27906 | AF36: 28 may | AG36: =IFERROR(TEXT(HLOOKUP(AD36,'Mano de obra'!$L$23:$BP$25,3,TRUE),"d mmm"),"") -> 8 Jun | AH36: =IF((($N36)*100)>='plan de producción'!AH$3,"x"," Material") -> Material | AI36: =IF((($N36)*100)>='plan de producción'!AI$3,"x","Armar ") -> Armar | AJ36: =IF((($N36)*100)>='plan de producción'!AJ$3,"x"," Resoldar") -> Resoldar | AK36: =IF((($N36)*100)>='plan de producción'!AK$3,"x"," Pulir") -> Pulir | AL36: =IF((($N36)*100)>='plan de producción'!AL$3,"x","Pintar ") -> Pintar | AM36: =IF((($N36)*100)>='plan de producción'!AM$3,"x","Ensamblar ") -> Ensamblar | AN36: =IF((($N36)*100)>='plan de producción'!AN$3,"x"," Empacar") -> Empacar
A37: Torno A. | B37: Torno E. | C37: Laser | D37: Carenaje | E37: Placas | F37: Tubos | G37: Inox. | H37: Pintu. | I37: Zinc | J37: Tornillos | K37: Rodam. | N37: 0 | Q37: 989 | R37: PETRA proyectos y construcciones | S37: xb442 | T37: =VLOOKUP(S37,'Precios y materiales '!$A$2:$B$147,2,FALSE) -> Sentadilla con discos | V37: Pereira | W37: Bioparques | Y37: 3151260.5 | Z37: =IFERROR(VLOOKUP(S37,'Precios y materiales '!$A:$C,3,FALSE),"") -> 3151260.5 | AA37: =(Y37*$AA$3)/'Mano de obra'!$C$9 -> 42.933534 | AB37: =AA37*(1-N37) -> 42.933534 | AC37: =AB37/9 -> 4.7703927 | AD37: =AD36+(AA37*(1-N37)) -> 603.2126 | AF37: 29 may | AG37: =IFERROR(TEXT(HLOOKUP(AD37,'Mano de obra'!$L$23:$BP$25,3,TRUE),"d mmm"),"") -> 9 Jun | AH37: =IF((($N37)*100)>='plan de producción'!AH$3,"x"," Material") -> Material | AI37: =IF((($N37)*100)>='plan de producción'!AI$3,"x","Armar ") -> Armar | AJ37: =IF((($N37)*100)>='plan de producción'!AJ$3,"x"," Resoldar") -> Resoldar | AK37: =IF((($N37)*100)>='plan de producción'!AK$3,"x"," Pulir") -> Pulir | AL37: =IF((($N37)*100)>='plan de producción'!AL$3,"x","Pintar ") -> Pintar | AM37: =IF((($N37)*100)>='plan de producción'!AM$3,"x","Ensamblar ") -> Ensamblar | AN37: =IF((($N37)*100)>='plan de producción'!AN$3,"x"," Empacar") -> Empacar
A38: Torno A. | B38: Torno E. | C38: Laser | D38: Carenaje | E38: Placas | F38: Tubos | G38: Inox. | H38: Pintu. | I38: Zinc | J38: Tornillos | K38: Rodam. | N38: 0 | Q38: 990 | R38: PETRA proyectos y construcciones | S38: xb437 | T38: =VLOOKUP(S38,'Precios y materiales '!$A$2:$B$147,2,FALSE) -> Press de pecho con discos | V38: Pereira | W38: Bioparques | Y38: 3151260.5 | Z38: =IFERROR(VLOOKUP(S38,'Precios y materiales '!$A:$C,3,FALSE),"") -> 3151260.5 | AA38: =(Y38*$AA$3)/'Mano de obra'!$C$9 -> 42.933534 | AB38: =AA38*(1-N38) -> 42.933534 | AC38: =AB38/9 -> 4.7703927 | AD38: =AD37+(AA38*(1-N38)) -> 646.14613 | AF38: 1 jun | AG38: =IFERROR(TEXT(HLOOKUP(AD38,'Mano de obra'!$L$23:$BP$25,3,TRUE),"d mmm"),"") -> 9 Jun | AH38: =IF((($N38)*100)>='plan de producción'!AH$3,"x"," Material") -> Material | AI38: =IF((($N38)*100)>='plan de producción'!AI$3,"x","Armar ") -> Armar | AJ38: =IF((($N38)*100)>='plan de producción'!AJ$3,"x"," Resoldar") -> Resoldar | AK38: =IF((($N38)*100)>='plan de producción'!AK$3,"x"," Pulir") -> Pulir | AL38: =IF((($N38)*100)>='plan de producción'!AL$3,"x","Pintar ") -> Pintar | AM38: =IF((($N38)*100)>='plan de producción'!AM$3,"x","Ensamblar ") -> Ensamblar | AN38: =IF((($N38)*100)>='plan de producción'!AN$3,"x"," Empacar") -> Empacar
A39: Torno A. | B39: Torno E. | C39: Laser | D39: Carenaje | E39: Placas | F39: Tubos | G39: Inox. | H39: Pintu. | I39: Zinc | J39: Tornillos | K39: Rodam. | N39: 0 | Q39: 991 | R39: PETRA proyectos y construcciones | S39: xb420 | T39: =VLOOKUP(S39,'Precios y materiales '!$A$2:$B$147,2,FALSE) -> Dominadas y Fondos bio | V39: Pereira | W39: Bioparques | Y39: 1841092 | Z39: =IFERROR(VLOOKUP(S39,'Precios y materiales '!$A:$C,3,FALSE),"") -> 1841092 | AA39: =(Y39*$AA$3)/'Mano de obra'!$C$9 -> 25.083482 | AB39: =AA39*(1-N39) -> 25.083482 | AC39: =AB39/9 -> 2.7870536 | AD39: =AD38+(AA39*(1-N39)) -> 671.22961 | AF39: 1 jun | AG39: =IFERROR(TEXT(HLOOKUP(AD39,'Mano de obra'!$L$23:$BP$25,3,TRUE),"d mmm"),"") -> 9 Jun | AH39: =IF((($N39)*100)>='plan de producción'!AH$3,"x"," Material") -> Material | AI39: =IF((($N39)*100)>='plan de producción'!AI$3,"x","Armar ") -> Armar | AJ39: =IF((($N39)*100)>='plan de producción'!AJ$3,"x"," Resoldar") -> Resoldar | AK39: =IF((($N39)*100)>='plan de producción'!AK$3,"x"," Pulir") -> Pulir | AL39: =IF((($N39)*100)>='plan de producción'!AL$3,"x","Pintar ") -> Pintar | AM39: =IF((($N39)*100)>='plan de producción'!AM$3,"x","Ensamblar ") -> Ensamblar | AN39: =IF((($N39)*100)>='plan de producción'!AN$3,"x"," Empacar") -> Empacar
A40: Torno A. | B40: Torno E. | C40: Laser | D40: Carenaje | E40: Placas | F40: Tubos | G40: Inox. | H40: Pintu. | I40: Zinc | J40: Tornillos | K40: Rodam. | N40: 0 | Q40: 992 | R40: PETRA proyectos y construcciones | S40: xb402 | T40: =VLOOKUP(S40,'Precios y materiales '!$A$2:$B$147,2,FALSE) -> Banco Abdominal doble | V40: Pereira | W40: Bioparques | Y40: 2484790 | Z40: =IFERROR(VLOOKUP(S40,'Precios y materiales '!$A:$C,3,FALSE),"") -> 2484790 | AA40: =(Y40*$AA$3)/'Mano de obra'!$C$9 -> 33.853379 | AB40: =AA40*(1-N40) -> 33.853379 | AC40: =AB40/9 -> 3.7614866 | AD40: =AD39+(AA40*(1-N40)) -> 705.08299 | AF40: 2 jun | AG40: =IFERROR(TEXT(HLOOKUP(AD40,'Mano de obra'!$L$23:$BP$25,3,TRUE),"d mmm"),"") -> 10 Jun | AH40: =IF((($N40)*100)>='plan de producción'!AH$3,"x"," Material") -> Material | AI40: =IF((($N40)*100)>='plan de producción'!AI$3,"x","Armar ") -> Armar | AJ40: =IF((($N40)*100)>='plan de producción'!AJ$3,"x"," Resoldar") -> Resoldar | AK40: =IF((($N40)*100)>='plan de producción'!AK$3,"x"," Pulir") -> Pulir | AL40: =IF((($N40)*100)>='plan de producción'!AL$3,"x","Pintar ") -> Pintar | AM40: =IF((($N40)*100)>='plan de producción'!AM$3,"x","Ensamblar ") -> Ensamblar | AN40: =IF((($N40)*100)>='plan de producción'!AN$3,"x"," Empacar") -> Empacar
A41: Torno A. | B41: Torno E. | C41: Laser | D41: Carenaje | E41: Placas | F41: Tubos | G41: Inox. | H41: Pintu. | I41: Zinc | J41: Tornillos | K41: Rodam. | N41: 0 | Q41: 993 | R41: PETRA proyectos y construcciones | S41: xb440 | T41: =VLOOKUP(S41,'Precios y materiales '!$A$2:$B$147,2,FALSE) -> Press de Pierna con discos | V41: Pereira | W41: Bioparques | Y41: 3163386 | Z41: =IFERROR(VLOOKUP(S41,'Precios y materiales '!$A:$C,3,FALSE),"") -> 3163386 | AA41: =(Y41*$AA$3)/'Mano de obra'!$C$9 -> 43.098735 | AB41: =AA41*(1-N41) -> 43.098735 | AC41: =AB41/9 -> 4.7887483 | AD41: =AD40+(AA41*(1-N41)) -> 748.18173 | AF41: 2 jun | AG41: =IFERROR(TEXT(HLOOKUP(AD41,'Mano de obra'!$L$23:$BP$25,3,TRUE),"d mmm"),"") -> 11 Jun | AH41: =IF((($N41)*100)>='plan de producción'!AH$3,"x"," Material") -> Material | AI41: =IF((($N41)*100)>='plan de producción'!AI$3,"x","Armar ") -> Armar | AJ41: =IF((($N41)*100)>='plan de producción'!AJ$3,"x"," Resoldar") -> Resoldar | AK41: =IF((($N41)*100)>='plan de producción'!AK$3,"x"," Pulir") -> Pulir | AL41: =IF((($N41)*100)>='plan de producción'!AL$3,"x","Pintar ") -> Pintar | AM41: =IF((($N41)*100)>='plan de producción'!AM$3,"x","Ensamblar ") -> Ensamblar | AN41: =IF((($N41)*100)>='plan de producción'!AN$3,"x"," Empacar") -> Empacar
A42: Torno A. | B42: Torno E. | C42: Laser | D42: Carenaje | E42: Placas | F42: Tubos | G42: Inox. | I42: Zinc | J42: Tornillos | K42: Rodam. | N42: 0 | Q42: 994 | R42: Inversiones aguas BARBOSA SAS | S42: xm171 | T42: =VLOOKUP(S42,'Precios y materiales '!$A$2:$B$147,2,FALSE) -> Sentadilla Smith con Poleas 2.0 | V42: CARTAGENA | W42: Musculación | Y42: 9600000 | Z42: =IFERROR(VLOOKUP(S42,'Precios y materiales '!$A:$C,3,FALSE),"") -> 9600000 | AA42: =(Y42*$AA$3)/'Mano de obra'!$C$9 -> 130.79272 | AB42: =AA42*(1-N42) -> 130.79272 | AC42: =AB42/9 -> 14.532524 | AD42: =AD41+(AA42*(1-N42)) -> 878.97444 | AF42: 4 jun | AG42: =IFERROR(TEXT(HLOOKUP(AD42,'Mano de obra'!$L$23:$BP$25,3,TRUE),"d mmm"),"") -> 15 Jun | AH42: =IF((($N42)*100)>='plan de producción'!AH$3,"x"," Material") -> Material | AI42: =IF((($N42)*100)>='plan de producción'!AI$3,"x","Armar ") -> Armar | AJ42: =IF((($N42)*100)>='plan de producción'!AJ$3,"x"," Resoldar") -> Resoldar | AK42: =IF((($N42)*100)>='plan de producción'!AK$3,"x"," Pulir") -> Pulir | AL42: =IF((($N42)*100)>='plan de producción'!AL$3,"x","Pintar ") -> Pintar | AM42: =IF((($N42)*100)>='plan de producción'!AM$3,"x","Ensamblar ") -> Ensamblar | AN42: =IF((($N42)*100)>='plan de producción'!AN$3,"x"," Empacar") -> Empacar
A43: Torno A. | B43: Torno E. | C43: Laser | D43: Carenaje | E43: Placas | F43: Tubos | G43: Inox. | H43: Pintu. | I43: Zinc | J43: Tornillos | K43: Rodam. | N43: 0 | Q43: 995 | R43: Consorcio del sol | S43: xb456 | T43: =VLOOKUP(S43,'Precios y materiales '!$A$2:$B$147,2,FALSE) -> Circuito de calistenia #2 | V43: Pereira | W43: Bioparques | Y43: 11008403 | Z43: =IFERROR(VLOOKUP(S43,'Precios y materiales '!$A:$C,3,FALSE),"") -> 0 | AA43: =(Y43*$AA$3)/'Mano de obra'!$C$9 -> 149.98114 | AB43: =AA43*(1-N43) -> 149.98114 | AC43: =AB43/9 -> 16.664571 | AD43: =AD42+(AA43*(1-N43)) -> 1028.9556 | AF43: 9 jun | AG43: =IFERROR(TEXT(HLOOKUP(AD43,'Mano de obra'!$L$23:$BP$25,3,TRUE),"d mmm"),"") -> 17 Jun | AH43: =IF((($N43)*100)>='plan de producción'!AH$3,"x"," Material") -> Material | AI43: =IF((($N43)*100)>='plan de producción'!AI$3,"x","Armar ") -> Armar | AJ43: =IF((($N43)*100)>='plan de producción'!AJ$3,"x"," Resoldar") -> Resoldar | AK43: =IF((($N43)*100)>='plan de producción'!AK$3,"x"," Pulir") -> Pulir | AL43: =IF((($N43)*100)>='plan de producción'!AL$3,"x","Pintar ") -> Pintar | AM43: =IF((($N43)*100)>='plan de producción'!AM$3,"x","Ensamblar ") -> Ensamblar | AN43: =IF((($N43)*100)>='plan de producción'!AN$3,"x"," Empacar") -> Empacar
A44: Torno A. | B44: Torno E. | C44: Laser | D44: Carenaje | E44: Placas | F44: Tubos | G44: Inox. | I44: Zinc | J44: Tornillos | K44: Rodam. | N44: 0 | Q44: 996 | R44: Consorcio del sol | S44: xb449 | T44: =VLOOKUP(S44,'Precios y materiales '!$A$2:$B$147,2,FALSE) -> Halon de espalda con discos | V44: Pereira | W44: Bioparques | Y44: 3151260.5 | Z44: =IFERROR(VLOOKUP(S44,'Precios y materiales '!$A:$C,3,FALSE),"") -> 3151260.5 | AA44: =(Y44*$AA$3)/'Mano de obra'!$C$9 -> 42.933534 | AB44: =AA44*(1-N44) -> 42.933534 | AC44: =AB44/9 -> 4.7703927 | AD44: =AD43+(AA44*(1-N44)) -> 1071.8891 | AF44: 9 jun | AG44: =IFERROR(TEXT(HLOOKUP(AD44,'Mano de obra'!$L$23:$BP$25,3,TRUE),"d mmm"),"") -> 17 Jun | AH44: =IF((($N44)*100)>='plan de producción'!AH$3,"x"," Material") -> Material | AI44: =IF((($N44)*100)>='plan de producción'!AI$3,"x","Armar ") -> Armar | AJ44: =IF((($N44)*100)>='plan de producción'!AJ$3,"x"," Resoldar") -> Resoldar | AK44: =IF((($N44)*100)>='plan de producción'!AK$3,"x"," Pulir") -> Pulir | AL44: =IF((($N44)*100)>='plan de producción'!AL$3,"x","Pintar ") -> Pintar | AM44: =IF((($N44)*100)>='plan de producción'!AM$3,"x","Ensamblar ") -> Ensamblar | AN44: =IF((($N44)*100)>='plan de producción'!AN$3,"x"," Empacar") -> Empacar
A45: Torno A. | B45: Torno E. | C45: Laser | D45: Carenaje | E45: Placas | F45: Tubos | G45: Inox. | H45: Pintu. | I45: Zinc | J45: Tornillos | K45: Rodam. | N45: 0 | Q45: 997 | R45: Consorcio del sol | S45: xb442 | T45: =VLOOKUP(S45,'Precios y materiales '!$A$2:$B$147,2,FALSE) -> Sentadilla con discos | V45: Pereira | W45: Bioparques | Y45: 3151260.5 | Z45: =IFERROR(VLOOKUP(S45,'Precios y materiales '!$A:$C,3,FALSE),"") -> 3151260.5 | AA45: =(Y45*$AA$3)/'Mano de obra'!$C$9 -> 42.933534 | AB45: =AA45*(1-N45) -> 42.933534 | AC45: =AB45/9 -> 4.7703927 | AD45: =AD44+(AA45*(1-N45)) -> 1114.8227 | AF45: 10 jun | AG45: =IFERROR(TEXT(HLOOKUP(AD45,'Mano de obra'!$L$23:$BP$25,3,TRUE),"d mmm"),"") -> 18 Jun | AH45: =IF((($N45)*100)>='plan de producción'!AH$3,"x"," Material") -> Material | AI45: =IF((($N45)*100)>='plan de producción'!AI$3,"x","Armar ") -> Armar | AJ45: =IF((($N45)*100)>='plan de producción'!AJ$3,"x"," Resoldar") -> Resoldar | AK45: =IF((($N45)*100)>='plan de producción'!AK$3,"x"," Pulir") -> Pulir | AL45: =IF((($N45)*100)>='plan de producción'!AL$3,"x","Pintar ") -> Pintar | AM45: =IF((($N45)*100)>='plan de producción'!AM$3,"x","Ensamblar ") -> Ensamblar | AN45: =IF((($N45)*100)>='plan de producción'!AN$3,"x"," Empacar") -> Empacar
A46: Torno A. | B46: Torno E. | C46: Laser | D46: Carenaje | E46: Placas | F46: Tubos | G46: Inox. | I46: Zinc | J46: Tornillos | K46: Rodam. | N46: 0 | Q46: 998 | R46: Consorcio del sol | S46: xb437 | T46: =VLOOKUP(S46,'Precios y materiales '!$A$2:$B$147,2,FALSE) -> Press de pecho con discos | V46: Pereira | W46: Bioparques | Y46: 3151260.5 | Z46: =IFERROR(VLOOKUP(S46,'Precios y materiales '!$A:$C,3,FALSE),"") -> 3151260.5 | AA46: =(Y46*$AA$3)/'Mano de obra'!$C$9 -> 42.933534 | AB46: =AA46*(1-N46) -> 42.933534 | AC46: =AB46/9 -> 4.7703927 | AD46: =AD45+(AA46*(1-N46)) -> 1157.7562 | AF46: 10 jun | AG46: =IFERROR(TEXT(HLOOKUP(AD46,'Mano de obra'!$L$23:$BP$25,3,TRUE),"d mmm"),"") -> 21 Jun | AH46: =IF((($N46)*100)>='plan de producción'!AH$3,"x"," Material") -> Material | AI46: =IF((($N46)*100)>='plan de producción'!AI$3,"x","Armar ") -> Armar | AJ46: =IF((($N46)*100)>='plan de producción'!AJ$3,"x"," Resoldar") -> Resoldar | AK46: =IF((($N46)*100)>='plan de producción'!AK$3,"x"," Pulir") -> Pulir | AL46: =IF((($N46)*100)>='plan de producción'!AL$3,"x","Pintar ") -> Pintar | AM46: =IF((($N46)*100)>='plan de producción'!AM$3,"x","Ensamblar ") -> Ensamblar | AN46: =IF((($N46)*100)>='plan de producción'!AN$3,"x"," Empacar") -> Empacar
A47: Torno A. | B47: Torno E. | C47: Laser | D47: Carenaje | E47: Placas | F47: Tubos | G47: Inox. | H47: Pintu. | I47: Zinc | J47: Tornillos | K47: Rodam. | N47: 0 | Q47: 999 | R47: Martha | S47: xm165 | T47: =VLOOKUP(S47,'Precios y materiales '!$A$2:$B$147,2,FALSE) -> Sentadilla Bulgara | U47: Blanco y rojo | V47: Manizales | W47: musculación | Y47: 490000 | Z47: =IFERROR(VLOOKUP(S47,'Precios y materiales '!$A:$C,3,FALSE),"") -> 490000 | AA47: =(Y47*$AA$3)/'Mano de obra'!$C$9 -> 6.6758783 | AB47: =AA47*(1-N47) -> 6.6758783 | AC47: =AB47/9 -> 0.74176426 | AD47: =AD46+(AA47*(1-N47)) -> 1164.4321 | AF47: 46190 | AG47: =IFERROR(TEXT(HLOOKUP(AD47,'Mano de obra'!$L$23:$BP$25,3,TRUE),"d mmm"),"") -> 21 Jun
A48: Torno A. | B48: Torno E. | C48: Laser | D48: Carenaje | E48: Placas | F48: Tubos | G48: Inox. | I48: Zinc | J48: Tornillos | K48: Rodam. | N48: 0 | Q48: 500 | R48: Martha | S48: xm148 | T48: =VLOOKUP(S48,'Precios y materiales '!$A$2:$B$147,2,FALSE) -> Polea Alta | U48: Blanco y rojo | V48: Manizales | W48: musculación | Y48: 3890000 | Z48: =IFERROR(VLOOKUP(S48,'Precios y materiales '!$A:$C,3,FALSE),"") -> 3890000 | AA48: =(Y48*$AA$3)/'Mano de obra'!$C$9 -> 52.998299 | AB48: =AA48*(1-N48) -> 52.998299 | AC48: =AB48/9 -> 5.8886999 | AD48: =AD47+(AA48*(1-N48)) -> 1217.4304 | AF48: 46191 | AG48: =IFERROR(TEXT(HLOOKUP(AD48,'Mano de obra'!$L$23:$BP$25,3,TRUE),"d mmm"),"") -> 22 Jun
A49: Torno A. | B49: Torno E. | C49: Laser | D49: Carenaje | E49: Placas | F49: Tubos | G49: Inox. | H49: Pintu. | I49: Zinc | J49: Tornillos | K49: Rodam. | N49: 0 | Q49: 501 | R49: Martha | S49: xm145 | T49: =VLOOKUP(S49,'Precios y materiales '!$A$2:$B$147,2,FALSE) -> Peck Deck doble función | U49: Blanco y rojo | V49: Manizales | W49: musculación | Y49: 3990000 | Z49: =IFERROR(VLOOKUP(S49,'Precios y materiales '!$A:$C,3,FALSE),"") -> 3990000 | AA49: =(Y49*$AA$3)/'Mano de obra'!$C$9 -> 54.360723 | AB49: =AA49*(1-N49) -> 54.360723 | AC49: =AB49/9 -> 6.0400804 | AD49: =AD48+(AA49*(1-N49)) -> 1271.7911 | AF49: 46194 | AG49: =IFERROR(TEXT(HLOOKUP(AD49,'Mano de obra'!$L$23:$BP$25,3,TRUE),"d mmm"),"") -> 22 Jun

Sheet Mano de obra
E1: 2026 | K1: l | L1: v | M1: s | N1: d | O1: l | P1: m | Q1: w | R1: j | S1: v | T1: s | U1: d | V1: l | W1: m | X1: w | Y1: j | Z1: v | AA1: s | AB1: d | AC1: l | AD1: m | AE1: w | AF1: j | AG1: v | AH1: s | AI1: d | AJ1: l | AK1: m | AL1: w | AM1: j | AN1: v | AO1: s | AP1: d | AQ1: l | AR1: m | AS1: w | AT1: j | AU1: v | AV1: s | AW1: d | AX1: l | AY1: m | AZ1: w | BA1: j | BB1: v | BC1: s | BD1: d | BE1: l | BF1: m | BG1: w | BH1: j | BI1: v | BJ1: s | BK1: d | BL1: l | BM1: m | BN1: w | BO1: j | BP1: v
E2: EMPLEADO | G2: Salario base | H2: BONIF | I2: Costo total | L2: 1 | M2: 2 | N2: 3 | O2: 4 | P2: 5 | Q2: 6 | R2: 7 | S2: 8 | T2: 9 | U2: 10 | V2: 11 | W2: 12 | X2: 13 | Y2: 14 | Z2: 15 | AA2: 16 | AB2: 17 | AC2: 18 | AD2: 19 | AE2: 20 | AF2: 21 | AG2: 22 | AH2: 23 | AI2: 24 | AJ2: 25 | AK2: 26 | AL2: 27 | AM2: 28 | AN2: 29 | AO2: 30 | AP2: 31 | AQ2: 32 | AR2: 33 | AS2: 34 | AT2: 35 | AU2: 36 | AV2: 37 | AW2: 38 | AX2: 39 | AY2: 40 | AZ2: 41 | BA2: 42 | BB2: 43 | BC2: 44 | BD2: 45 | BE2: 46 | BF2: 47 | BG2: 48 | BH2: 49 | BI2: 50 | BJ2: 51 | BK2: 52 | BL2: 53 | BM2: 54 | BN2: 55 | BO2: 56 | BP2: 57
E3: Nelly Muñoz Arias | F3: Ventas | G3: 3500000 | I3: =G3+H3 -> 3500000 | J3: 1 | L3: 1 | M3: 2 | N3: 3 | O3: 4 | P3: 5 | Q3: 6 | R3: 7 | S3: 8 | T3: 9 | U3: 10 | V3: 11 | W3: 12 | X3: 13 | Y3: 14 | Z3: 15 | AA3: 16 | AB3: 17 | AC3: 18 | AD3: 19 | AE3: 20 | AF3: 21 | AG3: 22 | AH3: 23 | AI3: 24 | AJ3: 25 | AK3: 26 | AL3: 27 | AM3: 28 | AN3: 29 | AO3: 30 | AP3: 31 | AQ3: 32 | AR3: 33 | AS3: 34 | AT3: 35 | AU3: 36 | AV3: 37 | AW3: 38 | AX3: 39 | AY3: 40 | AZ3: 41 | BA3: 42 | BB3: 43 | BC3: 44 | BD3: 45 | BE3: 46 | BF3: 47 | BG3: 48 | BH3: 49 | BI3: 50 | BJ3: 51 | BK3: 52 | BL3: 53 | BM3: 54 | BN3: 55 | BO3: 56 | BP3: 57
E4: Ana Maria Ramirez Torres | F4: Administración | G4: 950000 | I4: =G4+H4 -> 950000 | J4: 1
E5: Gina Lorena Lotero | F5: Administración | G5: 1750905 | H5: 400000 | I5: =G5+H5 -> 2150905 | J5: 14
E6: Santiago Alejandro Cardona | G6: 1750905 | I6: =G6+H6 -> 1750905
E7: TOTAL EMPLEADOS ADM+VTAS | F7: =COUNTIF(G3:G5,">0") -> 3 | G7: =SUM(G3:G5) -> 6200905 | I7: =(SUM(G3:H6))*(1+B12) -> 14365113
J8: Vacas debe sacar
A9: Costo por persona | B9: HORA | C9: =C14/C16 -> 22019.574 | D9: 1 | E9: Juan Felipe Martinez Aristizabal | F9: Armador | G9: 1750905 | H9: 1000000 | I9: =G9+H9 -> 2750905 | J9: 8 | K9: =(I9*(1+$B$12))/$C$16 -> 25034.691 | M9: =IF($E9="","",IF(OR(M$1="s",M$1="d"),"",IF(M$25<TODAY(),"",IF(M$1="v",6,9)))) | N9: =IF($E9="","",IF(OR(N$1="s",N$1="d"),"",IF(N$25<TODAY(),"",IF(N$1="v",6,9)))) | O9: =IF($E9="","",IF(OR(O$1="s",O$1="d"),"",IF(O$25<TODAY(),"",IF(O$1="v",6,9)))) | P9: =IF($E9="","",IF(OR(P$1="s",P$1="d"),"",IF(P$25<TODAY(),"",IF(P$1="v",6,9)))) | Q9: =IF($E9="","",IF(OR(Q$1="s",Q$1="d"),"",IF(Q$25<TODAY(),"",IF(Q$1="v",6,9)))) | R9: =IF($E9="","",IF(OR(R$1="s",R$1="d"),"",IF(R$25<TODAY(),"",IF(R$1="v",6,9)))) | S9: =IF($E9="","",IF(OR(S$1="s",S$1="d"),"",IF(S$25<TODAY(),"",IF(S$1="v",6,9)))) | T9: =IF($E9="","",IF(OR(T$1="s",T$1="d"),"",IF(T$25<TODAY(),"",IF(T$1="v",6,9)))) | ... W9: =IF($E9="","",IF(OR(W$1="s",W$1="d"),"",IF(W$25<TODAY(),"",IF(W$1="v",6,9)))) | AA9: =IF($E9="","",IF(OR(AA$1="s",AA$1="d"),"",IF(AA$25<TODAY(),"",IF(AA$1="v",6,9)))) | AB9: =IF($E9="","",IF(OR(AB$1="s",AB$1="d"),"",IF(AB$25<TODAY(),"",IF(AB$1="v",6,9)))) | AD9: =IF($E9="","",IF(OR(AD$1="s",AD$1="d"),"",IF(AD$25<TODAY(),"",IF(AD$1="v",6,9)))) | AE9: =IF($E9="","",IF(OR(AE$1="s",AE$1="d"),"",IF(AE$25<TODAY(),"",IF(AE$1="v",6,9)))) | AF9: =IF($E9="","",IF(OR(AF$1="s",AF$1="d"),"",IF(AF$25<TODAY(),"",IF(AF$1="v",6,9)))) | AG9: =IF($E9="","",IF(OR(AG$1="s",AG$1="d"),"",IF(AG$25<TODAY(),"",IF(AG$1="v",6,9)))) | AH9: =IF($E9="","",IF(OR(AH$1="s",AH$1="d"),"",IF(AH$25<TODAY(),"",IF(AH$1="v",6,9)))) | AI9: =IF($E9="","",IF(OR(AI$1="s",AI$1="d"),"",IF(AI$25<TODAY(),"",IF(AI$1="v",6,9)))) | AJ9: =IF($E9="","",IF(OR(AJ$1="s",AJ$1="d"),"",IF(AJ$25<TODAY(),"",IF(AJ$1="v",6,9)))) | AK9: =IF($E9="","",IF(OR(AK$1="s",AK$1="d"),"",IF(AK$25<TODAY(),"",IF(AK$1="v",6,9)))) | ... BP9: =IF($E9="","",IF(OR(BP$1="s",BP$1="d"),"",IF(BP$25<TODAY(),"",IF(BP$1="v",6,9)))) -> 6
A10: Costo por persona | B10: DIA | C10: =C14/C15 -> 208084.98 | D10: 2 | E10: Cristian Camilo Rodriguez Giraldo | F10: Tornero | G10: 1750905 | H10: 640000 | I10: =G10+H10 -> 2390905 | J10: 23 | K10: =(I10*(1+$B$12))/$C$16 -> 21758.501 | M10: =IF($E10="","",IF(OR(M$1="s",M$1="d"),"",IF(M$25<TODAY(),"",IF(M$1="v",6,9)))) | N10: =IF($E10="","",IF(OR(N$1="s",N$1="d"),"",IF(N$25<TODAY(),"",IF(N$1="v",6,9)))) | O10: =IF($E10="","",IF(OR(O$1="s",O$1="d"),"",IF(O$25<TODAY(),"",IF(O$1="v",6,9)))) | P10: =IF($E10="","",IF(OR(P$1="s",P$1="d"),"",IF(P$25<TODAY(),"",IF(P$1="v",6,9)))) | Q10: =IF($E10="","",IF(OR(Q$1="s",Q$1="d"),"",IF(Q$25<TODAY(),"",IF(Q$1="v",6,9)))) | R10: =IF($E10="","",IF(OR(R$1="s",R$1="d"),"",IF(R$25<TODAY(),"",IF(R$1="v",6,9)))) | S10: =IF($E10="","",IF(OR(S$1="s",S$1="d"),"",IF(S$25<TODAY(),"",IF(S$1="v",6,9)))) | T10: =IF($E10="","",IF(OR(T$1="s",T$1="d"),"",IF(T$25<TODAY(),"",IF(T$1="v",6,9)))) | ... AB10: =IF($E10="","",IF(OR(AB$1="s",AB$1="d"),"",IF(AB$25<TODAY(),"",IF(AB$1="v",6,9)))) | AD10: =IF($E10="","",IF(OR(AD$1="s",AD$1="d"),"",IF(AD$25<TODAY(),"",IF(AD$1="v",6,9)))) | AE10: =IF($E10="","",IF(OR(AE$1="s",AE$1="d"),"",IF(AE$25<TODAY(),"",IF(AE$1="v",6,9)))) | AF10: =IF($E10="","",IF(OR(AF$1="s",AF$1="d"),"",IF(AF$25<TODAY(),"",IF(AF$1="v",6,9)))) | AG10: =IF($E10="","",IF(OR(AG$1="s",AG$1="d"),"",IF(AG$25<TODAY(),"",IF(AG$1="v",6,9)))) | AH10: =IF($E10="","",IF(OR(AH$1="s",AH$1="d"),"",IF(AH$25<TODAY(),"",IF(AH$1="v",6,9)))) | AI10: =IF($E10="","",IF(OR(AI$1="s",AI$1="d"),"",IF(AI$25<TODAY(),"",IF(AI$1="v",6,9)))) | AJ10: =IF($E10="","",IF(OR(AJ$1="s",AJ$1="d"),"",IF(AJ$25<TODAY(),"",IF(AJ$1="v",6,9)))) | AK10: =IF($E10="","",IF(OR(AK$1="s",AK$1="d"),"",IF(AK$25<TODAY(),"",IF(AK$1="v",6,9)))) | ... BP10: =IF($E10="","",IF(OR(BP$1="s",BP$1="d"),"",IF(BP$25<TODAY(),"",IF(BP$1="v",6,9)))) -> 6
A11: Valor nomina PLANTA: | C11: =G23 -> 21776335 | D11: 3 | E11: Luis Alfonso Betancurth Osorio | F11: Pintor | G11: 1750905 | H11: 380000 | I11: =G11+H11 -> 2130905 | J11: 37 | K11: =(I11*(1+$B$12))/$C$16 -> 19392.363 | M11: =IF($E11="","",IF(OR(M$1="s",M$1="d"),"",IF(M$25<TODAY(),"",IF(M$1="v",6,9)))) | N11: =IF($E11="","",IF(OR(N$1="s",N$1="d"),"",IF(N$25<TODAY(),"",IF(N$1="v",6,9)))) | O11: =IF($E11="","",IF(OR(O$1="s",O$1="d"),"",IF(O$25<TODAY(),"",IF(O$1="v",6,9)))) | P11: =IF($E11="","",IF(OR(P$1="s",P$1="d"),"",IF(P$25<TODAY(),"",IF(P$1="v",6,9)))) | Q11: =IF($E11="","",IF(OR(Q$1="s",Q$1="d"),"",IF(Q$25<TODAY(),"",IF(Q$1="v",6,9)))) | R11: =IF($E11="","",IF(OR(R$1="s",R$1="d"),"",IF(R$25<TODAY(),"",IF(R$1="v",6,9)))) | S11: =IF($E11="","",IF(OR(S$1="s",S$1="d"),"",IF(S$25<TODAY(),"",IF(S$1="v",6,9)))) | T11: =IF($E11="","",IF(OR(T$1="s",T$1="d"),"",IF(T$25<TODAY(),"",IF(T$1="v",6,9)))) | ... AB11: =IF($E11="","",IF(OR(AB$1="s",AB$1="d"),"",IF(AB$25<TODAY(),"",IF(AB$1="v",6,9)))) | AD11: =IF($E11="","",IF(OR(AD$1="s",AD$1="d"),"",IF(AD$25<TODAY(),"",IF(AD$1="v",6,9)))) | AE11: =IF($E11="","",IF(OR(AE$1="s",AE$1="d"),"",IF(AE$25<TODAY(),"",IF(AE$1="v",6,9)))) | AF11: =IF($E11="","",IF(OR(AF$1="s",AF$1="d"),"",IF(AF$25<TODAY(),"",IF(AF$1="v",6,9)))) | AG11: =IF($E11="","",IF(OR(AG$1="s",AG$1="d"),"",IF(AG$25<TODAY(),"",IF(AG$1="v",6,9)))) | AH11: =IF($E11="","",IF(OR(AH$1="s",AH$1="d"),"",IF(AH$25<TODAY(),"",IF(AH$1="v",6,9)))) | AI11: =IF($E11="","",IF(OR(AI$1="s",AI$1="d"),"",IF(AI$25<TODAY(),"",IF(AI$1="v",6,9)))) | AJ11: =IF($E11="","",IF(OR(AJ$1="s",AJ$1="d"),"",IF(AJ$25<TODAY(),"",IF(AJ$1="v",6,9)))) | AK11: =IF($E11="","",IF(OR(AK$1="s",AK$1="d"),"",IF(AK$25<TODAY(),"",IF(AK$1="v",6,9)))) | ... BP11: =IF($E11="","",IF(OR(BP$1="s",BP$1="d"),"",IF(BP$25<TODAY(),"",IF(BP$1="v",6,9)))) -> 6
A12: Mas prestac. del : | B12: 0.72 | C12: =C11*(1+B12) -> 37455296 | D12: 4 | E12: Ariel Valencia Mina | F12: Varios | G12: 1750905 | H12: 200000 | I12: =G12+H12 -> 1950905 | J12: 9 | K12: =(I12*(1+$B$12))/$C$16 -> 17754.268 | M12: =IF($E12="","",IF(OR(M$1="s",M$1="d"),"",IF(M$25<TODAY(),"",IF(M$1="v",6,9)))) | N12: =IF($E12="","",IF(OR(N$1="s",N$1="d"),"",IF(N$25<TODAY(),"",IF(N$1="v",6,9)))) | O12: =IF($E12="","",IF(OR(O$1="s",O$1="d"),"",IF(O$25<TODAY(),"",IF(O$1="v",6,9)))) | P12: =IF($E12="","",IF(OR(P$1="s",P$1="d"),"",IF(P$25<TODAY(),"",IF(P$1="v",6,9)))) | Q12: =IF($E12="","",IF(OR(Q$1="s",Q$1="d"),"",IF(Q$25<TODAY(),"",IF(Q$1="v",6,9)))) | R12: =IF($E12="","",IF(OR(R$1="s",R$1="d"),"",IF(R$25<TODAY(),"",IF(R$1="v",6,9)))) | S12: =IF($E12="","",IF(OR(S$1="s",S$1="d"),"",IF(S$25<TODAY(),"",IF(S$1="v",6,9)))) | T12: =IF($E12="","",IF(OR(T$1="s",T$1="d"),"",IF(T$25<TODAY(),"",IF(T$1="v",6,9)))) | ... AB12: =IF($E12="","",IF(OR(AB$1="s",AB$1="d"),"",IF(AB$25<TODAY(),"",IF(AB$1="v",6,9)))) | AD12: =IF($E12="","",IF(OR(AD$1="s",AD$1="d"),"",IF(AD$25<TODAY(),"",IF(AD$1="v",6,9)))) | AE12: =IF($E12="","",IF(OR(AE$1="s",AE$1="d"),"",IF(AE$25<TODAY(),"",IF(AE$1="v",6,9)))) | AF12: =IF($E12="","",IF(OR(AF$1="s",AF$1="d"),"",IF(AF$25<TODAY(),"",IF(AF$1="v",6,9)))) | AG12: =IF($E12="","",IF(OR(AG$1="s",AG$1="d"),"",IF(AG$25<TODAY(),"",IF(AG$1="v",6,9)))) | AH12: =IF($E12="","",IF(OR(AH$1="s",AH$1="d"),"",IF(AH$25<TODAY(),"",IF(AH$1="v",6,9)))) | AI12: =IF($E12="","",IF(OR(AI$1="s",AI$1="d"),"",IF(AI$25<TODAY(),"",IF(AI$1="v",6,9)))) | AJ12: =IF($E12="","",IF(OR(AJ$1="s",AJ$1="d"),"",IF(AJ$25<TODAY(),"",IF(AJ$1="v",6,9)))) | AK12: =IF($E12="","",IF(OR(AK$1="s",AK$1="d"),"",IF(AK$25<TODAY(),"",IF(AK$1="v",6,9)))) | ... BP12: =IF($E12="","",IF(OR(BP$1="s",BP$1="d"),"",IF(BP$25<TODAY(),"",IF(BP$1="v",6,9)))) -> 6
A13: Cantidad empleados planta: | C13: =F23 -> 9 | D13: 5 | E13: Daniel Garcia Zaray | F13: Ensamblador | G13: 1750905 | H13: 300000 | I13: =G13+H13 -> 2050905 | J13: 8 | K13: =(I13*(1+$B$12))/$C$16 -> 18664.321 | M13: =IF($E13="","",IF(OR(M$1="s",M$1="d"),"",IF(M$25<TODAY(),"",IF(M$1="v",6,9)))) | N13: =IF($E13="","",IF(OR(N$1="s",N$1="d"),"",IF(N$25<TODAY(),"",IF(N$1="v",6,9)))) | O13: =IF($E13="","",IF(OR(O$1="s",O$1="d"),"",IF(O$25<TODAY(),"",IF(O$1="v",6,9)))) | P13: =IF($E13="","",IF(OR(P$1="s",P$1="d"),"",IF(P$25<TODAY(),"",IF(P$1="v",6,9)))) | Q13: =IF($E13="","",IF(OR(Q$1="s",Q$1="d"),"",IF(Q$25<TODAY(),"",IF(Q$1="v",6,9)))) | R13: =IF($E13="","",IF(OR(R$1="s",R$1="d"),"",IF(R$25<TODAY(),"",IF(R$1="v",6,9)))) | S13: =IF($E13="","",IF(OR(S$1="s",S$1="d"),"",IF(S$25<TODAY(),"",IF(S$1="v",6,9)))) | T13: =IF($E13="","",IF(OR(T$1="s",T$1="d"),"",IF(T$25<TODAY(),"",IF(T$1="v",6,9)))) | ... AB13: =IF($E13="","",IF(OR(AB$1="s",AB$1="d"),"",IF(AB$25<TODAY(),"",IF(AB$1="v",6,9)))) | AD13: =IF($E13="","",IF(OR(AD$1="s",AD$1="d"),"",IF(AD$25<TODAY(),"",IF(AD$1="v",6,9)))) | AE13: =IF($E13="","",IF(OR(AE$1="s",AE$1="d"),"",IF(AE$25<TODAY(),"",IF(AE$1="v",6,9)))) | AF13: =IF($E13="","",IF(OR(AF$1="s",AF$1="d"),"",IF(AF$25<TODAY(),"",IF(AF$1="v",6,9)))) | AG13: =IF($E13="","",IF(OR(AG$1="s",AG$1="d"),"",IF(AG$25<TODAY(),"",IF(AG$1="v",6,9)))) | AH13: =IF($E13="","",IF(OR(AH$1="s",AH$1="d"),"",IF(AH$25<TODAY(),"",IF(AH$1="v",6,9)))) | AI13: =IF($E13="","",IF(OR(AI$1="s",AI$1="d"),"",IF(AI$25<TODAY(),"",IF(AI$1="v",6,9)))) | AJ13: =IF($E13="","",IF(OR(AJ$1="s",AJ$1="d"),"",IF(AJ$25<TODAY(),"",IF(AJ$1="v",6,9)))) | AK13: =IF($E13="","",IF(OR(AK$1="s",AK$1="d"),"",IF(AK$25<TODAY(),"",IF(AK$1="v",6,9)))) | ... BP13: =IF($E13="","",IF(OR(BP$1="s",BP$1="d"),"",IF(BP$25<TODAY(),"",IF(BP$1="v",6,9)))) -> 6
A14: Sueldo integral promedio planta: | C14: =C12/C13 -> 4161699.6 | D14: 6 | E14: Daniel Rodrigo Duque Zapata | F14: asist ensamble | G14: 1750905 | H14: 200000 | I14: =G14+H14 -> 1950905 | J14: 9 | K14: =(I14*(1+$B$12))/$C$16 -> 17754.268 | M14: =IF($E14="","",IF(OR(M$1="s",M$1="d"),"",IF(M$25<TODAY(),"",IF(M$1="v",6,9)))) | N14: =IF($E14="","",IF(OR(N$1="s",N$1="d"),"",IF(N$25<TODAY(),"",IF(N$1="v",6,9)))) | O14: =IF($E14="","",IF(OR(O$1="s",O$1="d"),"",IF(O$25<TODAY(),"",IF(O$1="v",6,9)))) | P14: =IF($E14="","",IF(OR(P$1="s",P$1="d"),"",IF(P$25<TODAY(),"",IF(P$1="v",6,9)))) | Q14: =IF($E14="","",IF(OR(Q$1="s",Q$1="d"),"",IF(Q$25<TODAY(),"",IF(Q$1="v",6,9)))) | R14: =IF($E14="","",IF(OR(R$1="s",R$1="d"),"",IF(R$25<TODAY(),"",IF(R$1="v",6,9)))) | S14: =IF($E14="","",IF(OR(S$1="s",S$1="d"),"",IF(S$25<TODAY(),"",IF(S$1="v",6,9)))) | T14: =IF($E14="","",IF(OR(T$1="s",T$1="d"),"",IF(T$25<TODAY(),"",IF(T$1="v",6,9)))) | ... AB14: =IF($E14="","",IF(OR(AB$1="s",AB$1="d"),"",IF(AB$25<TODAY(),"",IF(AB$1="v",6,9)))) | AD14: =IF($E14="","",IF(OR(AD$1="s",AD$1="d"),"",IF(AD$25<TODAY(),"",IF(AD$1="v",6,9)))) | AE14: =IF($E14="","",IF(OR(AE$1="s",AE$1="d"),"",IF(AE$25<TODAY(),"",IF(AE$1="v",6,9)))) | AF14: =IF($E14="","",IF(OR(AF$1="s",AF$1="d"),"",IF(AF$25<TODAY(),"",IF(AF$1="v",6,9)))) | AG14: =IF($E14="","",IF(OR(AG$1="s",AG$1="d"),"",IF(AG$25<TODAY(),"",IF(AG$1="v",6,9)))) | AH14: =IF($E14="","",IF(OR(AH$1="s",AH$1="d"),"",IF(AH$25<TODAY(),"",IF(AH$1="v",6,9)))) | AI14: =IF($E14="","",IF(OR(AI$1="s",AI$1="d"),"",IF(AI$25<TODAY(),"",IF(AI$1="v",6,9)))) | AJ14: =IF($E14="","",IF(OR(AJ$1="s",AJ$1="d"),"",IF(AJ$25<TODAY(),"",IF(AJ$1="v",6,9)))) | AK14: =IF($E14="","",IF(OR(AK$1="s",AK$1="d"),"",IF(AK$25<TODAY(),"",IF(AK$1="v",6,9)))) | ... BP14: =IF($E14="","",IF(OR(BP$1="s",BP$1="d"),"",IF(BP$25<TODAY(),"",IF(BP$1="v",6,9)))) -> 6
A15: Dias laborales en: | C15: 20 | D15: 7 | E15: Jose Fernando Gaviria | F15: Armador | H15: 3500000 | I15: =G15+H15 -> 3500000 | K15: =(I15*(1+$B$12))/$C$16 -> 31851.852 | M15: =IF($E15="","",IF(OR(M$1="s",M$1="d"),"",IF(M$25<TODAY(),"",IF(M$1="v",6,9)))) | N15: =IF($E15="","",IF(OR(N$1="s",N$1="d"),"",IF(N$25<TODAY(),"",IF(N$1="v",6,9)))) | O15: =IF($E15="","",IF(OR(O$1="s",O$1="d"),"",IF(O$25<TODAY(),"",IF(O$1="v",6,9)))) | P15: =IF($E15="","",IF(OR(P$1="s",P$1="d"),"",IF(P$25<TODAY(),"",IF(P$1="v",6,9)))) | Q15: =IF($E15="","",IF(OR(Q$1="s",Q$1="d"),"",IF(Q$25<TODAY(),"",IF(Q$1="v",6,9)))) | R15: =IF($E15="","",IF(OR(R$1="s",R$1="d"),"",IF(R$25<TODAY(),"",IF(R$1="v",6,9)))) | S15: =IF($E15="","",IF(OR(S$1="s",S$1="d"),"",IF(S$25<TODAY(),"",IF(S$1="v",6,9)))) | T15: =IF($E15="","",IF(OR(T$1="s",T$1="d"),"",IF(T$25<TODAY(),"",IF(T$1="v",6,9)))) | ... AB15: =IF($E15="","",IF(OR(AB$1="s",AB$1="d"),"",IF(AB$25<TODAY(),"",IF(AB$1="v",6,9)))) | AD15: =IF($E15="","",IF(OR(AD$1="s",AD$1="d"),"",IF(AD$25<TODAY(),"",IF(AD$1="v",6,9)))) | AE15: =IF($E15="","",IF(OR(AE$1="s",AE$1="d"),"",IF(AE$25<TODAY(),"",IF(AE$1="v",6,9)))) | AF15: =IF($E15="","",IF(OR(AF$1="s",AF$1="d"),"",IF(AF$25<TODAY(),"",IF(AF$1="v",6,9)))) | AG15: =IF($E15="","",IF(OR(AG$1="s",AG$1="d"),"",IF(AG$25<TODAY(),"",IF(AG$1="v",6,9)))) | AH15: =IF($E15="","",IF(OR(AH$1="s",AH$1="d"),"",IF(AH$25<TODAY(),"",IF(AH$1="v",6,9)))) | AI15: =IF($E15="","",IF(OR(AI$1="s",AI$1="d"),"",IF(AI$25<TODAY(),"",IF(AI$1="v",6,9)))) | AJ15: =IF($E15="","",IF(OR(AJ$1="s",AJ$1="d"),"",IF(AJ$25<TODAY(),"",IF(AJ$1="v",6,9)))) | AK15: =IF($E15="","",IF(OR(AK$1="s",AK$1="d"),"",IF(AK$25<TODAY(),"",IF(AK$1="v",6,9)))) | ... BP15: =IF($E15="","",IF(OR(BP$1="s",BP$1="d"),"",IF(BP$25<TODAY(),"",IF(BP$1="v",6,9)))) -> 6
A16: Horas laborales x persona mes promedio 2025: | C16: 189 | D16: 8 | E16: Germán | F16: Armador | G16: 1750905 | H16: 300000 | I16: =G16+H16 -> 2050905 | J16: 4 | K16: =(I16*(1+$B$12))/$C$16 -> 18664.321 | M16: =IF($E16="","",IF(OR(M$1="s",M$1="d"),"",IF(M$25<TODAY(),"",IF(M$1="v",6,9)))) | N16: =IF($E16="","",IF(OR(N$1="s",N$1="d"),"",IF(N$25<TODAY(),"",IF(N$1="v",6,9)))) | O16: =IF($E16="","",IF(OR(O$1="s",O$1="d"),"",IF(O$25<TODAY(),"",IF(O$1="v",6,9)))) | P16: =IF($E16="","",IF(OR(P$1="s",P$1="d"),"",IF(P$25<TODAY(),"",IF(P$1="v",6,9)))) | Q16: =IF($E16="","",IF(OR(Q$1="s",Q$1="d"),"",IF(Q$25<TODAY(),"",IF(Q$1="v",6,9)))) | R16: =IF($E16="","",IF(OR(R$1="s",R$1="d"),"",IF(R$25<TODAY(),"",IF(R$1="v",6,9)))) | S16: =IF($E16="","",IF(OR(S$1="s",S$1="d"),"",IF(S$25<TODAY(),"",IF(S$1="v",6,9)))) | T16: =IF($E16="","",IF(OR(T$1="s",T$1="d"),"",IF(T$25<TODAY(),"",IF(T$1="v",6,9)))) | ... AB16: =IF($E16="","",IF(OR(AB$1="s",AB$1="d"),"",IF(AB$25<TODAY(),"",IF(AB$1="v",6,9)))) | AD16: =IF($E16="","",IF(OR(AD$1="s",AD$1="d"),"",IF(AD$25<TODAY(),"",IF(AD$1="v",6,9)))) | AE16: =IF($E16="","",IF(OR(AE$1="s",AE$1="d"),"",IF(AE$25<TODAY(),"",IF(AE$1="v",6,9)))) | AF16: =IF($E16="","",IF(OR(AF$1="s",AF$1="d"),"",IF(AF$25<TODAY(),"",IF(AF$1="v",6,9)))) | AG16: =IF($E16="","",IF(OR(AG$1="s",AG$1="d"),"",IF(AG$25<TODAY(),"",IF(AG$1="v",6,9)))) | AH16: =IF($E16="","",IF(OR(AH$1="s",AH$1="d"),"",IF(AH$25<TODAY(),"",IF(AH$1="v",6,9)))) | AI16: =IF($E16="","",IF(OR(AI$1="s",AI$1="d"),"",IF(AI$25<TODAY(),"",IF(AI$1="v",6,9)))) | AJ16: =IF($E16="","",IF(OR(AJ$1="s",AJ$1="d"),"",IF(AJ$25<TODAY(),"",IF(AJ$1="v",6,9)))) | AK16: =IF($E16="","",IF(OR(AK$1="s",AK$1="d"),"",IF(AK$25<TODAY(),"",IF(AK$1="v",6,9)))) | ... BP16: =IF($E16="","",IF(OR(BP$1="s",BP$1="d"),"",IF(BP$25<TODAY(),"",IF(BP$1="v",6,9)))) -> 6
D17: 9 | E17: Santiago Cardenas | F17: Armador | H17: 3000000 | I17: =G17+H17 -> 3000000 | K17: =(I17*(1+$B$12))/$C$16 -> 27301.587
K18: =(I18*(1+$B$12))/$C$16 -> 0 | L18: =IF($E18="","",IF(OR(L$1="s",L$1="d"),"",IF(L$25<TODAY(),"",IF(L$1="v",6,9)))) | M18: =IF($E18="","",IF(OR(M$1="s",M$1="d"),"",IF(M$25<TODAY(),"",IF(M$1="v",6,9)))) | N18: =IF($E18="","",IF(OR(N$1="s",N$1="d"),"",IF(N$25<TODAY(),"",IF(N$1="v",6,9)))) | O18: =IF($E18="","",IF(OR(O$1="s",O$1="d"),"",IF(O$25<TODAY(),"",IF(O$1="v",6,9)))) | P18: =IF($E18="","",IF(OR(P$1="s",P$1="d"),"",IF(P$25<TODAY(),"",IF(P$1="v",6,9)))) | Q18: =IF($E18="","",IF(OR(Q$1="s",Q$1="d"),"",IF(Q$25<TODAY(),"",IF(Q$1="v",6,9)))) | R18: =IF($E18="","",IF(OR(R$1="s",R$1="d"),"",IF(R$25<TODAY(),"",IF(R$1="v",6,9)))) | S18: =IF($E18="","",IF(OR(S$1="s",S$1="d"),"",IF(S$25<TODAY(),"",IF(S$1="v",6,9)))) | ... AB18: =IF($E18="","",IF(OR(AB$1="s",AB$1="d"),"",IF(AB$25<TODAY(),"",IF(AB$1="v",6,9)))) | AD18: =IF($E18="","",IF(OR(AD$1="s",AD$1="d"),"",IF(AD$25<TODAY(),"",IF(AD$1="v",6,9)))) | AE18: =IF($E18="","",IF(OR(AE$1="s",AE$1="d"),"",IF(AE$25<TODAY(),"",IF(AE$1="v",6,9)))) | AF18: =IF($E18="","",IF(OR(AF$1="s",AF$1="d"),"",IF(AF$25<TODAY(),"",IF(AF$1="v",6,9)))) | AG18: =IF($E18="","",IF(OR(AG$1="s",AG$1="d"),"",IF(AG$25<TODAY(),"",IF(AG$1="v",6,9)))) | AH18: =IF($E18="","",IF(OR(AH$1="s",AH$1="d"),"",IF(AH$25<TODAY(),"",IF(AH$1="v",6,9)))) | AI18: =IF($E18="","",IF(OR(AI$1="s",AI$1="d"),"",IF(AI$25<TODAY(),"",IF(AI$1="v",6,9)))) | AJ18: =IF($E18="","",IF(OR(AJ$1="s",AJ$1="d"),"",IF(AJ$25<TODAY(),"",IF(AJ$1="v",6,9)))) | AK18: =IF($E18="","",IF(OR(AK$1="s",AK$1="d"),"",IF(AK$25<TODAY(),"",IF(AK$1="v",6,9)))) | ... BP18: =IF($E18="","",IF(OR(BP$1="s",BP$1="d"),"",IF(BP$25<TODAY(),"",IF(BP$1="v",6,9))))
L19: =IF($E19="","",IF(OR(L$1="s",L$1="d"),"",IF(L$25<TODAY(),"",IF(L$1="v",6,9)))) | M19: =IF($E19="","",IF(OR(M$1="s",M$1="d"),"",IF(M$25<TODAY(),"",IF(M$1="v",6,9)))) | N19: =IF($E19="","",IF(OR(N$1="s",N$1="d"),"",IF(N$25<TODAY(),"",IF(N$1="v",6,9)))) | O19: =IF($E19="","",IF(OR(O$1="s",O$1="d"),"",IF(O$25<TODAY(),"",IF(O$1="v",6,9)))) | P19: =IF($E19="","",IF(OR(P$1="s",P$1="d"),"",IF(P$25<TODAY(),"",IF(P$1="v",6,9)))) | Q19: =IF($E19="","",IF(OR(Q$1="s",Q$1="d"),"",IF(Q$25<TODAY(),"",IF(Q$1="v",6,9)))) | R19: =IF($E19="","",IF(OR(R$1="s",R$1="d"),"",IF(R$25<TODAY(),"",IF(R$1="v",6,9)))) | S19: =IF($E19="","",IF(OR(S$1="s",S$1="d"),"",IF(S$25<TODAY(),"",IF(S$1="v",6,9)))) | ... AB19: =IF($E19="","",IF(OR(AB$1="s",AB$1="d"),"",IF(AB$25<TODAY(),"",IF(AB$1="v",6,9)))) | AD19: =IF($E19="","",IF(OR(AD$1="s",AD$1="d"),"",IF(AD$25<TODAY(),"",IF(AD$1="v",6,9)))) | AE19: =IF($E19="","",IF(OR(AE$1="s",AE$1="d"),"",IF(AE$25<TODAY(),"",IF(AE$1="v",6,9)))) | AF19: =IF($E19="","",IF(OR(AF$1="s",AF$1="d"),"",IF(AF$25<TODAY(),"",IF(AF$1="v",6,9)))) | AG19: =IF($E19="","",IF(OR(AG$1="s",AG$1="d"),"",IF(AG$25<TODAY(),"",IF(AG$1="v",6,9)))) | AH19: =IF($E19="","",IF(OR(AH$1="s",AH$1="d"),"",IF(AH$25<TODAY(),"",IF(AH$1="v",6,9)))) | AI19: =IF($E19="","",IF(OR(AI$1="s",AI$1="d"),"",IF(AI$25<TODAY(),"",IF(AI$1="v",6,9)))) | AJ19: =IF($E19="","",IF(OR(AJ$1="s",AJ$1="d"),"",IF(AJ$25<TODAY(),"",IF(AJ$1="v",6,9)))) | AK19: =IF($E19="","",IF(OR(AK$1="s",AK$1="d"),"",IF(AK$25<TODAY(),"",IF(AK$1="v",6,9)))) | ... BP19: =IF($E19="","",IF(OR(BP$1="s",BP$1="d"),"",IF(BP$25<TODAY(),"",IF(BP$1="v",6,9))))
L20: =IF($E20="","",IF(OR(L$1="s",L$1="d"),"",IF(L$25<TODAY(),"",IF(L$1="v",6,9)))) | M20: =IF($E20="","",IF(OR(M$1="s",M$1="d"),"",IF(M$25<TODAY(),"",IF(M$1="v",6,9)))) | N20: =IF($E20="","",IF(OR(N$1="s",N$1="d"),"",IF(N$25<TODAY(),"",IF(N$1="v",6,9)))) | O20: =IF($E20="","",IF(OR(O$1="s",O$1="d"),"",IF(O$25<TODAY(),"",IF(O$1="v",6,9)))) | P20: =IF($E20="","",IF(OR(P$1="s",P$1="d"),"",IF(P$25<TODAY(),"",IF(P$1="v",6,9)))) | Q20: =IF($E20="","",IF(OR(Q$1="s",Q$1="d"),"",IF(Q$25<TODAY(),"",IF(Q$1="v",6,9)))) | R20: =IF($E20="","",IF(OR(R$1="s",R$1="d"),"",IF(#REF!<TODAY(),"",IF(R$1="v",6,9)))) | S20: =IF($E20="","",IF(OR(S$1="s",S$1="d"),"",IF(R$25<TODAY(),"",IF(S$1="v",6,9)))) | T20: =IF($E20="","",IF(OR(T$1="s",T$1="d"),"",IF(S$25<TODAY(),"",IF(T$1="v",6,9)))) | U20: =IF($E20="","",IF(OR(U$1="s",U$1="d"),"",IF(T$25<TODAY(),"",IF(U$1="v",6,9)))) | V20: =IF($E20="","",IF(OR(V$1="s",V$1="d"),"",IF(U$25<TODAY(),"",IF(V$1="v",6,9)))) | W20: =IF($E20="","",IF(OR(W$1="s",W$1="d"),"",IF(V$25<TODAY(),"",IF(W$1="v",6,9)))) | X20: =IF($E20="","",IF(OR(X$1="s",X$1="d"),"",IF(W$25<TODAY(),"",IF(X$1="v",6,9)))) | Y20: =IF($E20="","",IF(OR(Y$1="s",Y$1="d"),"",IF(X$25<TODAY(),"",IF(Y$1="v",6,9)))) | Z20: =IF($E20="","",IF(OR(Z$1="s",Z$1="d"),"",IF(Y$25<TODAY(),"",IF(Z$1="v",6,9)))) | ... BP20: =IF($E20="","",IF(OR(BP$1="s",BP$1="d"),"",IF(BO$25<TODAY(),"",IF(BP$1="v",6,9))))
G21: =SUBTOTAL(9,G9:G18) -> 12256335 | H21: =SUBTOTAL(9,H9:H18) -> 9520000 | I21: =SUBTOTAL(9,I9:I18) -> 21776335 | L21: =IF($E21="","",IF(OR(L$1="s",L$1="d"),"",IF(L$25<TODAY(),"",IF(L$1="v",6,9)))) | M21: =IF($E21="","",IF(OR(M$1="s",M$1="d"),"",IF(M$25<TODAY(),"",IF(M$1="v",6,9)))) | N21: =IF($E21="","",IF(OR(N$1="s",N$1="d"),"",IF(N$25<TODAY(),"",IF(N$1="v",6,9)))) | O21: =IF($E21="","",IF(OR(O$1="s",O$1="d"),"",IF(O$25<TODAY(),"",IF(O$1="v",6,9)))) | P21: =IF($E21="","",IF(OR(P$1="s",P$1="d"),"",IF(P$25<TODAY(),"",IF(P$1="v",6,9)))) | Q21: =IF($E21="","",IF(OR(Q$1="s",Q$1="d"),"",IF(Q$25<TODAY(),"",IF(Q$1="v",6,9)))) | R21: =IF($E21="","",IF(OR(R$1="s",R$1="d"),"",IF(#REF!<TODAY(),"",IF(R$1="v",6,9)))) | S21: =IF($E21="","",IF(OR(S$1="s",S$1="d"),"",IF(R$25<TODAY(),"",IF(S$1="v",6,9)))) | T21: =IF($E21="","",IF(OR(T$1="s",T$1="d"),"",IF(S$25<TODAY(),"",IF(T$1="v",6,9)))) | U21: =IF($E21="","",IF(OR(U$1="s",U$1="d"),"",IF(T$25<TODAY(),"",IF(U$1="v",6,9)))) | V21: =IF($E21="","",IF(OR(V$1="s",V$1="d"),"",IF(U$25<TODAY(),"",IF(V$1="v",6,9)))) | W21: =IF($E21="","",IF(OR(W$1="s",W$1="d"),"",IF(V$25<TODAY(),"",IF(W$1="v",6,9)))) | X21: =IF($E21="","",IF(OR(X$1="s",X$1="d"),"",IF(W$25<TODAY(),"",IF(X$1="v",6,9)))) | Y21: =IF($E21="","",IF(OR(Y$1="s",Y$1="d"),"",IF(X$25<TODAY(),"",IF(Y$1="v",6,9)))) | Z21: =IF($E21="","",IF(OR(Z$1="s",Z$1="d"),"",IF(Y$25<TODAY(),"",IF(Z$1="v",6,9)))) | ... BP21: =IF($E21="","",IF(OR(BP$1="s",BP$1="d"),"",IF(BO$25<TODAY(),"",IF(BP$1="v",6,9))))
E22: CAPACIDAD TOTAL LABORAL DE LA PLANTA EN EL MES Y CADA DIA: | J22: Horas día: | K22: =SUM(#REF!) -> #REF! | L22: =SUM(L9:L21) -> 0 | M22: =SUM(M9:M21) -> 0 | N22: =SUM(N9:N21) -> 0 | O22: =SUM(O9:O21) -> 0 | P22: =SUM(P9:P21) -> 0 | Q22: =SUM(Q9:Q21) -> 0 | R22: =SUM(R9:R21) -> 0 | S22: =SUM(S9:S21) -> 0 | ... BP22: =SUM(BP9:BP21) -> 48
E23: TOTAL EMPLEADOS PLANTA | F23: =COUNTIF(I9:I18,">0") -> 9 | G23: =SUM(I9:I18) -> 21776335 | J23: Acum horas mes: | K23: =K22 -> #REF! | L23: =0+L22 -> 0 | M23: =L23+M22 -> 0 | N23: =M23+N22 -> 0 | O23: =N23+O22 -> 0 | P23: =O23+P22 -> 0 | Q23: =P23+Q22 -> 0 | R23: =Q23+R22 -> 0 | S23: =R23+S22 -> 0 | T23: =S23+T22 -> 0 | ... BP23: =BO23+BP22 -> 1464
L25: 46143 | M25: 46144 | N25: 46145 | O25: 46146 | P25: 46147 | Q25: 46148 | R25: 46149 | S25: 46150 | T25: 46151 | U25: 46152 | V25: 46153 | W25: 46154 | X25: 46155 | Y25: 46156 | Z25: 46157 | AA25: 46158 | AB25: 46159 | AC25: 46160 | AD25: 46161 | AE25: 46162 | AF25: 46163 | AG25: 46164 | AH25: 46165 | AI25: 46166 | AJ25: 46167 | AK25: 46168 | AL25: 46169 | AM25: 46170 | AN25: 46171 | AO25: 46172 | AP25: 46173 | AQ25: 46174 | AR25: 46175 | AS25: 46176 | AT25: 46177 | AU25: 46178 | AV25: 46179 | AW25: 46180 | AX25: 46181 | AY25: 46182 | AZ25: 46183 | BA25: 46184 | BB25: 46185 | BC25: 46186 | BD25: 46187 | BE25: 46188 | BF25: 46189 | BG25: 46190 | BH25: 46191 | BI25: 46192 | BJ25: 46193 | BK25: 46194 | BL25: 46195 | BM25: 46196 | BN25: 46197 | BO25: 46198 | BP25: 46199

Sheet Precios y materiales 
B1: =COUNTA(#REF!) -> 1 | C1: REVISADOS CON NELLY agosto 11 de 2025
A2: CODIGO | B2: Producto | C2: Precios antes de iva
A3: XM105 | B3: Banco Multifunción | C3: 1190000
A4: XM184 | B4: Prensa Atletica 3.0 lineal | C4: 3990000
A5: XM161 | B5: Rack Sentadilla | C5: 1990000
A6: XM100 | B6: Abductor Aductor | C6: 4000000
A7: XM108 | B7: Banco olímpico plano | C7: 1490000
A8: XM114 | B8: Crossover Compacta | C8: 5600000
A9: XM120 | B9: Flexo Extensor | C9: 3990000
A10: XM121 | B10: Flexor Acostado | C10: 3600000
A11: XM170 | B11: Sentadilla Smith 2.0 | C11: 4450000
A12: XM104 | B12: Banco hombro peso libre | C12: 650000
A13: XM109 | B13: Banco plano peso libre | C13: 590000
A14: XM130 | B14: Hammer remo | C14: 2100000
... A26: XM143 | B26: Patada glúteo peso libre | C26: 1650000
A27: XM168 | B27: Sentadilla hack up 2.0
A28: XM169 | B28: Sentadilla Sissy | C28: 590000
A29: XM106 | B29: Banco olímpico declinado | C29: 1790000
A30: XM113 | B30: Crossover clásica | C30: 5600000
A31: XM116 | B31: Elevador de pelvis | C31: 2490000
A32: XM126 | B32: Hammer de Hombro | C32: 2520000
A33: XM129 | B33: Hammer Pecho Plana | C33: 2520000
A34: XM140 | B34: Pantorrillero | C34: 1390000
A35: XM160 | B35: Prensa pendular | C35: 4055462.2
A36: XM166 | B36: Sentadilla combinada | C36: 3350000
A37: XM172 | B37: Torre auxiliar | C37: 3990000
A38: XM175 | B38: Jaula de potencia
A39: XM176 | B39: Sentadilla con pantorrillero | C39: 2700000
A40: XM186 | B40: Dominadas y fondos asistido | C40: 4650000
A41: XM103 | B41: Banco abdominal | C41: 1090000
A42: XM110 | B42: Banco predicador con placas | C42: 4180000
A43: XM156 | B43: Prensa 90 | C43: 2990000
A44: XM162 | B44: Remo en punta | C44: 1750000
A45: XM167 | B45: Sentadilla Hack Up
A46: XM171 | B46: Sentadilla Smith con Poleas 2.0 | C46: 9600000
A47: XM193 | B47: Hammer isolateral vuelos con placas | C47: 4016806.7
A48: XB438 | B48: Press de Pecho Doble | C48: 2968824
A49: XB400 | B49: Banco Abdominal inclinado | C49: 1952017
A50: XB401 | B50: Banco Abdominal Calistenia
A51: XB402 | B51: Banco Abdominal doble | C51: 2484790
A52: XB403 | B52: Banco Plano Abdominal
A53: XB404 | B53: Banco Press de Hombro
A54: XB405 | B54: Barra Lineal al aire libre
A55: XB406 | B55: Barra paralela calistenia
A56: XB407 | B56: Barra Polea Alta
A57: XB408 | B57: Barras asimétricas o dominadas dobles
A58: XB409 | B58: Barras Asimétricas Sencilla
A59: XB410 | B59: Barras Combinadas
A60: XB411 | B60: Barras Combinadas con Abdominales
A61: XB412 | B61: Barras Dominadas Triangulares
A62: XB413 | B62: Barras Mini Combinadas
A63: XB414 | B63: Barras Paralelas | C63: 1672268.9
A64: XB415 | B64: Base Estiramiento
A65: XB416 | B65: Bicicleta | C65: 2088991.6
A66: XM191 | B66: Abductor | C66: 4000000
A67: XM909 | B67: accesorio fondos para jaula | C67: 139411.76
A68: XM192 | B68: Aductor | C68: 4000000
A69: XM195 | B69: BANCO OLIMPICO MULTIPÓSICIÓN. | C69: 2243697.5
A70: XH700 | B70: Bancos planos linea hogar | C70: 252100.84
A71: XB414 | B71: BARRAS PARALELAS | C71: 1672268.9
A72: XB416 | B72: BICICLETA | C72: 2088991.6
A73: _ | B73: CAMPO VACIO
A74: XJ505 | B74: Carrusel | C74: 4477731.1
A75: XB455 | B75: CIRCUITO DE CALISTENIA #1 | C75: 10534454
A76: XJ504 | B76: Columpio doble | C76: 3445798.3
A77: XJ506 | B77: Deslizadero sencillo | C77: 3327731.1
A78: XM115 | B78: Dominadas y fondos | C78: 1690000
A79: XB425 | B79: ESQUI | C79: 2354537.8
A80: XB426 | B80: EXTENSOR | C80: 2412521
A81: XM188 | B81: fondos triceps peso libre | C81: 1900000
A82: GA018 | B82: GARANTIA 18 HORAS | C82: =(16000*18)/0.25 -> 1152000
A83: GA009 | B83: GARANTIA 9 HORAS | C83: =(16000*9)/0.25 -> 576000
A84: XM179 | B84: hammer isolateral vuelos | C84: 1700000
A85: XM127 | B85: Hammer pecho declinada | C85: 2520000
A86: XM131 | B86: Hammer tibia | C86: 690000
A87: XM132 | B87: Hiperextensor Horizontal | C87: 1390000
A88: XM133 | B88: Hiperextensor Inclinado | C88: 1390000
A89: XM | B89: INSTALACIÓN
A90: XM134 | B90: Jaula de Crossfit (Solo funcional, sin polea)
A91: XM181 | B91: Jaula de Potencia para peso | C91: 2880000
A92: XM138 | B92: Multifuerza 4 estaciones (Precio variable según equipos) | C92: 15000000
A93: XM139 | B93: Multifuerza 8 estaciones (Precio variable según equipos) | C93: 32000000
A94: XJ507 | B94: PARQUE INFANTIL #2 | C94: 10863866
A95: XM911 | B95: PIVOTE DE BARRA PARA JAULA | C95: 168067.23
A96: acce | B96: Portapesos en maquina
A97: PE | B97: PROYECTO ESPECIAL
A98: XA908 | B98: Rack para mancuernas 2 NIVELES | C98: 600000
A99: XM908 | B99: Rack para mancuernas 2 niveles | C99: 600000
A100: XM906 | B100: Rack para mancuernas 3niveles | C100: 700000
A101: XM165 | B101: Sentadilla Bulgara | C101: 490000
A102: XM185 | B102: Sentadilla Hack Up 3.0 Lineal | C102: 3990000
A103: XM187 | B103: Sentadilla Smith con poleas 3.0 | C103: 10020168
A104: XM194 | B104: sentadilla Sumo | C104: 2519000
A105: XB553 | B105: Sube y baja Doble | C105: 3306722.7
A106: XB417 | B106: Brida Antivandalismo
A107: XB418 | B107: Circuito de Calistenia
A108: XB419 | B108: COLLARIN (PAR)
A109: XB420 | B109: Dominadas y Fondos bio | C109: 1841092
A110: XB421 | B110: Elevación hombro con discos | C110: 3000000
A111: XB422 | B111: Eliptica | C111: 2311681
...

Sheet despachados
N3: 1 | Q3: 5 | R3: Carlos Ariel E | S3: XM108 | T3: Banco olímpico plano | U3: NEGRO 100% | V3: Manizales | W3: Musculación | Y3: 1490000 | Z3: 1490000 | AA3: 20.30012 | AB3: 0 | AC3: 0 | AD3: 0 | AE3: PROPIA. | AF3: 5 mar | AH3: x | AI3: x | AJ3: x | AK3: x | AL3: x | AM3: x | AN3: x | AO3: 0
N4: 1 | Q4: 923 | R4: Carlos Ariel E | S4: XM185 | T4: Sentadilla Hack Up 3.0 Lineal | U4: NEGRO 100% | V4: Manizales | W4: Musculación | Y4: 3990000 | Z4: 3990000 | AA4: 54.360723 | AB4: 0 | AC4: 0 | AD4: 0 | AE4: santiago | AF4: 8 mar | AH4: x | AI4: x | AJ4: x | AK4: x | AL4: x | AM4: x | AN4: x | AO4: 0
N5: 1 | Q5: 925 | R5: YEISON BOHORQUES | S5: XM115 | T5: Dominadas y fondos | U5: NEGRO 100% | V5: Dosquebradas | W5: Musculación | Y5: 1690000 | Z5: 1690000 | AA5: 23.024968 | AB5: 0 | AC5: 0 | AD5: 0 | AE5: santiago | AF5: 8 mar | AH5: x | AI5: x | AJ5: x | AK5: x | AL5: x | AM5: x | AN5: x | AO5: 0
N6: 1 | Q6: 926 | R6: grupo ignea sas | S6: xb455 | T6: CIRCUITO DE CALISTENIA #1 | U6: Naranja amarillo | V6: Pereira | W6: Bioparques | Y6: 11008403 | Z6: 10534454 | AA6: 149.98114 | AB6: 0 | AC6: 0 | AD6: 0 | AE6: PIPE | AF6: 10 mar | AH6: x | AI6: x | AJ6: x | AK6: x | AL6: x | AM6: x | AN6: x | AO6: 0
N7: 1 | Q7: 927 | R7: grupo ignea sas | S7: XB449 | T7: Halon de espalda con discos | U7: Naranja amarillo | V7: Pereira | W7: Bioparques | Y7: 3210084 | Z7: 3151260.5 | AA7: 43.73496 | AB7: 0 | AC7: 0 | AD7: 0 | AE7: GERMAN | AF7: 11 mar | AH7: x | AI7: x | AJ7: x | AK7: x | AL7: x | AM7: x | AN7: x | AO7: 0
N8: 1 | Q8: 928 | R8: grupo ignea sas | S8: XB442 | T8: Sentadilla con discos | U8: Naranja amarillo | V8: Pereira | W8: Bioparques | Y8: 3210084 | Z8: 3151260.5 | AA8: 43.73496 | AB8: 0 | AC8: 0 | AD8: 0 | AE8: JOSE | AF8: 11 mar | AH8: x | AI8: x | AJ8: x | AK8: x | AL8: x | AM8: x | AN8: x | AO8: 0
N9: 1 | Q9: 929 | R9: grupo ignea sas | S9: XB437 | T9: Press de pecho con discos | U9: Naranja amarillo | V9: Pereira | W9: Bioparques | Y9: 3210084 | Z9: 3151260.5 | AA9: 43.73496 | AB9: 0 | AC9: 0 | AD9: 0 | AE9: JOSE | AF9: 12 mar | AH9: x | AI9: x | AJ9: x | AK9: x | AL9: x | AM9: x | AN9: x | AO9: 0
K10: ANCLAR | N10: 1 | Q10: 930 | R10: CINCI CONSTRUC. | S10: XB442 | T10: Sentadilla con Discos | U10: Naranja amarillo | V10: Pereira | W10: Bioparques | Y10: 3151260.5 | Z10: 3151260.5 | AA10: 42.933534 | AB10: 0 | AD10: 0 | AE10: JOSE | AF10: 12 mar | AH10: x | AI10: x | AJ10: x | AK10: x | AL10: x | AM10: x | AN10: x | AO10: 0
K11: ANCLAR | N11: 1 | Q11: 931 | R11: CINCI CONSTRUC. | S11: XB449 | T11: Halon de Espalda con Discos | U11: Naranja amarillo | V11: Pereira | W11: Bioparques | Y11: 3151260.5 | Z11: 3151260.5 | AA11: 42.933534 | AB11: 0 | AC11: 0 | AD11: 0 | AE11: EXISTE + SANTIAGO | AF11: 15 mar | AH11: x | AI11: x | AJ11: x | AK11: x | AL11: x | AM11: x | AN11: x | AO11: 0
G12: . | K12: . | N12: 1 | Q12: 932 | R12: CINCI CONSTRUC. | S12: XB434 | T12: Press de espalda doble | U12: Naranja amarillo | V12: Pereira | W12: Bioparques | Y12: 2968823.5 | Z12: 2968824 | AA12: 40.447969 | AB12: 0 | AC12: 0 | AD12: 0 | AE12: JOSE | AF12: 15 mar | AH12: x | AI12: x | AJ12: x | AK12: x | AL12: x | AM12: x | AN12: x | AO12: 0
G13: . | K13: . | N13: 1 | Q13: 933 | R13: CINCI CONSTRUC. | S13: XB438 | T13: Press de Pecho Doble | U13: Naranja amarillo | V13: Pereira | W13: Bioparques | Y13: 2968823.5 | Z13: 2968824 | AA13: 40.447969 | AB13: 0 | AC13: 0 | AD13: 0 | AE13: JOSE | AF13: 16 mar | AH13: x | AI13: x | AJ13: x | AK13: x | AL13: x | AM13: x | AN13: x | AO13: 0
G14: . | K14: . | N14: 1 | Q14: 934 | R14: CINCI CONSTRUC. | S14: XB432 | T14: Prensa de Pierna Doble | U14: Naranja amarillo | V14: Pereira | W14: Bioparques | Y14: 2885882.4 | Z14: 2885882 | AA14: 39.317958 | AB14: 0 | AC14: 0 | AD14: 0 | AE14: santiago | AF14: 16 mar | AH14: x | AI14: x | AJ14: x | AK14: x | AL14: x | AM14: x | AN14: x | AO14: 0
G15: . | K15: . | N15: 1 | Q15: 935 | R15: INTELIGENTES S.A.S | S15: XB442 | T15: Sentadilla con Discos | U15: Naranja amarillo | V15: Pereira | W15: Bioparques | Y15: 3163865.5 | Z15: 3151260.5 | AA15: 43.105268 | AB15: 0 | AC15: 0 | AD15: 0 | AE15: JOSE | AF15: 16 mar | AH15: x | AI15: x | AJ15: x | AK15: x | AL15: x | AM15: x | AN15: x | AO15: 0
G16: . | K16: . | N16: 1 | Q16: 936 | R16: INTELIGENTES S.A.S | S16: XB438 | T16: Press de Pecho Doble | U16: Naranja amarillo | V16: Pereira | W16: Bioparques | Y16: 2968823.5 | Z16: 2968824 | AA16: 40.447969 | AB16: 0 | AC16: 0 | AD16: 0 | AE16: JOSE | AF16: 17 mar | AH16: x | AI16: x | AJ16: x | AK16: x | AL16: x | AM16: x | AN16: x | AO16: 0
G17: . | K17: . | N17: 1 | Q17: 937 | R17: INTELIGENTES S.A.S | S17: XB438 | T17: Press de Pecho Doble | U17: Naranja amarillo | V17: Pereira | W17: Bioparques | Y17: 2968823.5 | Z17: 2968824 | AA17: 40.447969 | AB17: 0 | AC17: 0 | AD17: 0 | AE17: JOSE | AF17: 17 mar | AH17: x | AI17: x | AJ17: x | AK17: x | AL17: x | AM17: x | AN17: x | AO17: 0
G18: . | K18: . | N18: 1 | Q18: 938 | R18: INTELIGENTES S.A.S | S18: XB437 | T18: Press de Pecho con Discos | U18: Naranja amarillo | V18: Pereira | W18: Bioparques | Y18: 3163865.5 | Z18: 3151260.5 | AA18: 43.105268 | AB18: 0 | AC18: 0 | AD18: 0 | AE18: JOSE | AF18: 18 mar | AH18: x | AI18: x | AJ18: x | AK18: x | AL18: x | AM18: x | AN18: x | AO18: 0
G19: . | K19: . | N19: 1 | Q19: 939 | R19: INTELIGENTES S.A.S | S19: XB449 | T19: Halon de Espalda con Discos | U19: Naranja amarillo | V19: Pereira | W19: Bioparques | Y19: 2995798.3 | Z19: 3151260.5 | AA19: 40.81548 | AB19: 0 | AC19: 0 | AD19: 0 | AE19: santiago | AF19: 18 mar | AH19: x | AI19: x | AJ19: x | AK19: x | AL19: x | AM19: x | AN19: x | AO19: 0
N20: 1 | Q20: 943 | R20: Giovana Martinez | S20: XM112 | T20: constructor gluteo | U20: verde vitra + negro | V20: Tunja | W20: Musculación | Y20: 2190000 | Z20: 2190000 | AA20: 29.837089 | AB20: 0 | AC20: 0 | AD20: 0 | AE20: JOSE | AF20: 26 mar | AH20: x | AI20: x | AJ20: x | AK20: x | AL20: x | AM20: x | AN20: x | AO20: 0
N21: 1 | Q21: 944 | R21: Giovana Martinez | S21: xm165 | T21: sentadilla bulgara | U21: verde vitra | V21: Tunja | W21: Musculación | Y21: 490000 | Z21: 490000 | AA21: 6.6758783 | AB21: 0 | AC21: 0 | AD21: 0 | AE21: santiago | AF21: 26 mar | AH21: x | AI21: x | AJ21: x | AK21: x | AL21: x | AM21: x | AN21: x | AO21: 0
N22: 1 | Q22: 945 | R22: Giovana Martinez | S22: xm165 | T22: sentadilla bulgara | U22: verde vitra | V22: Tunja | W22: Musculación | Y22: 490000 | Z22: 490000 | AA22: 6.6758783 | AB22: 0 | AC22: 0 | AD22: 0 | AE22: santiago | AF22: 26 mar | AH22: x | AI22: x | AJ22: x | AK22: x | AL22: x | AM22: x | AN22: x | AO22: 0
N23: 1 | Q23: 949 | R23: Giovana Martinez | S23: XC100 | T23: Objetivo de bola pared | U23: Solo negro | V23: tunja | W23: Musculación | Y23: 237731 | Z23: 237731 | AA23: 3.2389046 | AB23: 0 | AC23: 0 | AD23: 0 | AF23: 30 mar | AH23: x | AI23: x | AJ23: x | AK23: x | AL23: x | AM23: x | AN23: x | AO23: 0
N24: 1 | Q24: 950 | R24: Giovana Martinez | S24: XC100 | T24: Objetivo de bola pared | U24: Solo negro | V24: Tunja | W24: Musculación | Y24: 237731 | Z24: 237731 | AA24: 3.2389046 | AB24: 0 | AC24: 0 | AD24: 0 | AF24: 30 mar | AH24: x | AI24: x | AJ24: x | AK24: x | AL24: x | AM24: x | AN24: x | AO24: 0
N25: 0.8 | T25: Eliptica Bengala - GARANTIA | U25: cortar tornillos | V25: Manizales | Y25: 990000 | AA25: 13.487999 | AB25: 2.6975998 | AC25: 0.29973331 | AD25: 2.6975998
N26: 1 | T26: Nicolas COELLO - GARANTIA | U26: Daniel volvio. | V26: BOGOTA | Y26: 990000 | AA26: 13.487999 | AB26: 0 | AC26: 0 | AD26: 2.6975998
N27: 1 | P27: DEUDA | Q27: 940 | R27: EMAS | S27: XS846 | T27: DEUDA DRA LUZ MARIA. CERVANTES | U27: Rojo verde | V27: Manizales | W27: Bioparques | Y27: 8000000 | Z27: 0 | AA27: 108.99393 | AB27: 0 | AC27: 0 | AD27: 0 | AF27: 23 mar | AH27: x | AI27: x | AJ27: x | AK27: x | AL27: x | AM27: x | AN27: x
N28: 1 | Q28: 946 | R28: Carlos Calderón DUCAGYM | S28: XM130 | T28: Hammer remo | U28: Negro rojo | V28: Manizales | W28: Musculación | Y28: 2100000 | Z28: 2100000 | AA28: 28.610907 | AB28: 0 | AC28: 0 | AD28: 0 | AE28: JOSE | AF28: 29 mar | AH28: x | AI28: x | AJ28: x | AK28: x | AL28: x | AM28: x | AN28: x
N29: 1 | Q29: 947 | R29: Carlos Calderón DUCAGYM | S29: XM133 | T29: Hiperextensor Inclinado | U29: Negro rojo | V29: Manizales | W29: Musculación | Y29: 1390000 | Z29: 1390000 | AA29: 18.937696 | AB29: 0 | AC29: 0 | AD29: 0 | AE29: santiago | AF29: 46110 | AH29: x | AI29: x | AJ29: x | AK29: x | AL29: x | AM29: x | AN29: x
N30: 1 | Q30: 948 | R30: Carlos Calderón DUCAGYM | S30: XM170 | T30: Sentadilla Smith 2.0 | U30: Negro rojo | V30: Manizales | W30: Musculación | Y30: 4450000 | Z30: 4450000 | AA30: 60.627875 | AB30: 0 | AC30: 0 | AD30: 0 | AE30: JOSE | AF30: 30 mar | AH30: x | AI30: x | AJ30: x | AK30: x | AL30: x | AM30: x | AN30: x
N31: 1 | Q31: 951 | R31: Alejandro Arango | S31: XM143 | T31: Patada gluteo peso libre | U31: solo rojo | V31: Ginebra | W31: Musculación | Y31: 1650000 | Z31: 1650000 | AA31: 22.479998 | AB31: 0 | AC31: 0 | AD31: 0 | AE31: santiago | AF31: 6 abr | AH31: x | AI31: x | AJ31: x | AK31: x | AL31: x | AM31: x | AN31: x
N32: 1 | Q32: 955 | R32: Rafael Berdella | S32: XM128 | T32: hammer pecho inclinado | U32: AMARILLO NEGRO | V32: Cereté | Y32: 2520000 | Z32: 2520000 | AA32: 34.333089 | AB32: 0 | AC32: 0 | AD32: 0 | AF32: 8 abr | AH32: x | AI32: x | AJ32: x | AK32: x | AL32: x | AM32: x | AN32: x
N33: 1 | Q33: 952 | R33: CONST JYP SAS | S33: XM148 | T33: Polea alta. | U33: Negra +Rojo med | V33: Manizales | W33: Musculación | Y33: 3890000 | Z33: 3890000 | AA33: 52.998299 | AB33: 0 | AC33: 0 | AD33: 0 | AF33: 6 abr | AH33: x | AI33: x | AJ33: x | AK33: x | AL33: x | AM33: x | AN33: x
N34: 1 | Q34: 954 | R34: CONST JYP SAS | S34: XM171 | T34: Sentadilla Smith con poleas 2.0 | U34: Negra +Rojo med | V34: Manizales | W34: Musculación | Y34: 9600000 | Z34: 9600000 | AA34: 130.79272 | AB34: 0 | AC34: 0 | AD34: 0 | AE34: jose | AF34: 8 abr | AH34: x | AI34: x | AJ34: x | AK34: x | AL34: x | AM34: x | AN34: x
N35: 1 | Q35: 828 | R35: CONST JYP SAS | S35: XM175 | T35: Jaula de potencia | U35: Negra 100% | V35: Manizales | W35: Musculación | Y35: 2220084 | Z35: 0 | AA35: 30.246961 | AB35: 0 | AC35: 0 | AD35: 0 | AE35: PROPIA. | AF35: 6 abr | AH35: x | AI35: x | AJ35: x | AK35: x | AL35: x | AM35: x | AN35: x
N36: 1 | Q36: 953 | R36: CONST JYP SAS | S36: XM909 | T36: Accesorio fondos para jaula | U36: Negra 100% | V36: Manizales | W36: Musculación | Y36: 147815.13 | Z36: 139411.76 | AA36: 2.013869 | AB36: 0 | AC36: 0 | AD36: 0 | AF36: 6 abr | AH36: x | AI36: x | AJ36: x | AK36: x | AL36: x | AM36: x | AN36: x
N37: 1 | Q37: 956 | R37: Construobras-Daniel Herrera | S37: XB442 | T37: Sentadilla con Discos | U37: Naranja amarillo | V37: Pereira | W37: Bioparques | Y37: 3151260.5 | Z37: 3151260.5 | AA37: 42.933534 | AB37: 0 | AC37: 0 | AD37: 0 | AF37: 8 abr | AG37: 20 may | AH37: x | AI37: x | AJ37: x | AK37: x | AL37: x | AM37: x | AN37: x
N38: 1 | Q38: 957 | R38: Construobras-Daniel Herrera | S38: XB449 | T38: Halon de Espalda con Discos | U38: Naranja amarillo | V38: Pereira | W38: Bioparques | Y38: 3151260.5 | Z38: 3151260.5 | AA38: 42.933534 | AB38: 0 | AC38: 0 | AD38: 0 | AE38: santiago | AF38: 9 abr | AG38: 20 may | AH38: x | AI38: x | AJ38: x | AK38: x | AL38: x | AM38: x | AN38: x
N39: 1 | Q39: 958 | R39: Construobras-Daniel Herrera | S39: XB434 | T39: Press de espalda doble | U39: Naranja amarillo | V39: Pereira | W39: Bioparques | Y39: 2968823.5 | Z39: 2968824 | AA39: 40.447969 | AB39: 0 | AC39: 0 | AD39: 0 | AF39: 12 abr | AG39: 20 may | AH39: x | AI39: x | AJ39: x | AK39: x | AL39: x | AM39: x | AN39: x
N40: 1 | Q40: 959 | R40: Construobras-Daniel Herrera | S40: XB438 | T40: Press de Pecho Doble | U40: Naranja amarillo | V40: Pereira | W40: Bioparques | Y40: 2968823.5 | Z40: 2968824 | AA40: 40.447969 | AB40: 0 | AC40: 0 | AD40: 0 | AF40: 12 abr | AG40: 20 may | AH40: x | AI40: x | AJ40: x | AK40: x | AL40: x | AM40: x | AN40: x
N41: 1 | Q41: 960 | R41: Construobras-Daniel Herrera | S41: XB432 | T41: Prensa de Pierna Doble | U41: Naranja amarillo | V41: Pereira | W41: Bioparques | Y41: 2885882.4 | Z41: 2885882 | AA41: 39.317958 | AB41: 0 | AC41: 0 | AD41: 0 | AE41: santiago | AF41: 13 abr | AG41: 20 may | AH41: x | AI41: x | AJ41: x | AK41: x | AL41: x | AM41: x | AN41: x
N42: 1 | Q42: 961 | R42: cinci | S42: xb456 | T42: Circuito de calistenia #2 | U42: Naranja amarillo | V42: Pereira | W42: Bioparques | Y42: 11008403 | Z42: 0 | AA42: 149.98114 | AB42: 0 | AC42: 0 | AD42: 0 | AE42: PIPE | AF42: 22 abr | AG42: 20 may | AH42: x | AI42: x | AJ42: x | AK42: x | AL42: x | AM42: x | AN42: x
N43: 1 | Q43: 942 | R43: Seminario mayor | S43: XM184 | T43: Prensa Atletica 3.0 lineal | U43: Negro amarillo | V43: Manizales | W43: Musculación | Y43: 3990000 | Z43: 3990000 | AA43: 54.360723 | AB43: 0 | AC43: 0 | AD43: 0 | AE43: santiago | AF43: 26 mar | AG43: 20 may | AH43: x | AI43: x | AJ43: x | AK43: x | AL43: x | AM43: x | AN43: x
N44: 1 | Q44: 941 | R44: Seminario mayor | S44: XS847 | T44: Mantenimiento MAQUINA 1. | U44: Negro amarillo | V44: Manizales | W44: Musculación | Y44: 2000000 | Z44: 0 | AA44: 27.248483 | AB44: 0 | AC44: 0 | AD44: 0 | AF44: 25 mar | AG44: 20 may | AH44: x | AI44: x | AJ44: x | AK44: x | AL44: x | AM44: x | AN44: x
N45: 1 | Q45: 941 | R45: Seminario mayor | S45: XS847 | T45: Mantenimiento MAQUINA 2 | U45: Negro amarillo | V45: Manizales | W45: Musculación | Y45: 2000000 | Z45: 0 | AA45: 27.248483 | AB45: 0 | AC45: 0 | AD45: 0 | AF45: 25 mar | AG45: 20 may | AH45: x | AI45: x | AJ45: x | AK45: x | AL45: x | AM45: x | AN45: x
N46: 1 | Q46: 941 | R46: Seminario mayor | S46: XS847 | T46: Mantenimiento MAQUINA 3 | U46: Negro amarillo | V46: Manizales | W46: Musculación | Y46: 2000000 | Z46: 0 | AA46: 27.248483 | AB46: 0 | AC46: 0 | AD46: 0 | AF46: 25 mar | AG46: 20 may | AH46: x | AI46: x | AJ46: x | AK46: x | AL46: x | AM46: x | AN46: x
N47: 1 | Q47: 941 | R47: Seminario mayor | S47: XS847 | T47: Mantenimiento MAQUINA 4 | U47: Negro amarillo | V47: Manizales | W47: Musculación | Y47: 2000000 | Z47: 0 | AA47: 27.248483 | AB47: 0 | AC47: 0 | AD47: 0 | AF47: 25 mar | AG47: 20 may | AH47: x | AI47: x | AJ47: x | AK47: x | AL47: x | AM47: x | AN47: x
N48: 1 | Q48: 941 | R48: Seminario mayor | S48: XS847 | T48: Mantenimiento MAQUINA 5 | U48: Negro amarillo | V48: Manizales | W48: Musculación | Y48: 2000000 | Z48: 0 | AA48: 27.248483 | AB48: 0 | AC48: 0 | AD48: 0 | AF48: 25 mar | AG48: 20 may | AH48: x | AI48: x | AJ48: x | AK48: x | AL48: x | AM48: x | AN48: x
A49: Torno A. | B49: Torno E. | M49: Cojines | N49: 1 | Q49: 962 | R49: Belfan R. Landazabl | S49: XM165 | T49: Sentadilla Bulgara | U49: negro 100% | V49: Saravena | W49: Musculación | Y49: 490000 | Z49: 490000 | AA49: 6.6758783 | AB49: 0 | AC49: 0 | AD49: 0 | AF49: 27 abr | AG49: 20 may | AH49: x | AI49: x | AJ49: x | AK49: x | AL49: x | AM49: x | AN49: x
A50: Torno A. | B50: Torno E. | M50: Cojines | N50: 1 | Q50: 963 | R50: Belfan R. Landazabl | S50: XM165 | T50: Sentadilla Bulgara | U50: negro 100% | V50: Saravena | W50: Musculación | Y50: 490000 | Z50: 490000 | AA50: 6.6758783 | AB50: 0 | AC50: 0 | AD50: 0 | AF50: 27 abr | AG50: 20 may | AH50: x | AI50: x | AJ50: x | AK50: x | AL50: x | AM50: x | AN50: x
B51: Torno E. | M51: Cojines | N51: 1 | Q51: 21 | R51: Belfan R. Landazabl | S51: XM112 | T51: Constructor glúteo | U51: negro 100% | V51: Saravena | W51: Musculación | Y51: 2190000 | Z51: 2190000 | AA51: 29.837089 | AB51: 0 | AC51: 0 | AD51: 0 | AF51: 22 abr | AG51: 20 may | AH51: x | AI51: x | AJ51: x | AK51: x | AL51: x | AM51: x | AN51: x
B52: Torno E. | M52: Cojines | N52: 1 | Q52: 964 | R52: Belfan R. Landazabl | S52: XM112 | T52: Constructor glúteo | U52: negro 100% | V52: Saravena | W52: Musculación | Y52: 2190000 | Z52: 2190000 | AA52: 29.837089 | AB52: 0 | AC52: 0 | AD52: 0 | AF52: 27 abr | AG52: 20 may | AH52: x | AI52: x | AJ52: x | AK52: x | AL52: x | AM52: x | AN52: x
A53: Torno A. | B53: Torno E. | H53: Pintu. | K53: Rodam. | N53: 1 | Q53: 965 | R53: EMAS - Aranjuez | S53: XS850 | T53: Pres de pecho sencillo | U53: Rojo verde | V53: Manizales | W53: Bioparques | Y53: 1418750 | AA53: 19.329393 | AB53: 0 | AC53: 0 | AD53: 0 | AF53: 28 abr | AG53: 20 may | AH53: x | AI53: x | AJ53: x | AK53: x | AL53: x | AM53: x | AN53: x
A54: Torno A. | B54: Torno E. | H54: Pintu. | K54: Rodam. | N54: 1 | Q54: 966 | R54: EMAS - Aranjuez | S54: XS850 | T54: Press de pierna sencillo | U54: Rojo verde | V54: Manizales | W54: Bioparques | Y54: 1418750 | AA54: 19.329393 | AB54: 0 | AC54: 0 | AD54: 0 | AF54: 28 abr | AG54: 20 may | AH54: x | AI54: x | AJ54: x | AK54: x | AL54: x | AM54: x | AN54: x
A55: Torno A. | B55: Torno E. | H55: Pintu. | K55: Rodam. | N55: 1 | Q55: 967 | R55: EMAS - Aranjuez | S55: XS850 | T55: Press de espalda doble | U55: Rojo verde | V55: Manizales | W55: Bioparques | Y55: 1418750 | AA55: 19.329393 | AB55: 0 | AC55: 0 | AD55: 0 | AF55: 28 abr | AG55: 20 may | AH55: x | AI55: x | AJ55: x | AK55: x | AL55: x | AM55: x | AN55: x
A56: Torno A. | B56: Torno E. | H56: Pintu. | K56: Rodam. | N56: 1 | Q56: 968 | R56: EMAS - Aranjuez | S56: XS850 | T56: Pony | U56: Rojo verde | V56: Manizales | W56: Bioparques | Y56: 1418750 | AA56: 19.329393 | AB56: 0 | AC56: 0 | AD56: 0 | AF56: 28 abr | AG56: 20 may | AH56: x | AI56: x | AJ56: x | AK56: x | AL56: x | AM56: x | AN56: x
A57: Torno A. | B57: Torno E. | K57: Rodam. | N57: 1 | Q57: 969 | R57: EMAS - Chachafruto | S57: XS849 | T57: Sentadilla con discos | U57: Rojo verde | V57: Manizales | W57: Bioparques | Y57: 1500000 | AA57: 20.436362 | AB57: 0 | AC57: 0 | AD57: 0 | AF57: 28 abr | AG57: 20 may | AH57: x | AI57: x | AJ57: x | AK57: x | AL57: x | AM57: x | AN57: x
A58: Torno A. | B58: Torno E. | K58: Rodam. | N58: 1 | Q58: 970 | R58: EMAS - Chachafruto | S58: XS849 | T58: Eliptica | U58: Rojo verde | V58: Manizales | W58: Bioparques | Y58: 1500000 | AA58: 20.436362 | AB58: 0 | AC58: 0 | AD58: 0 | AF58: 28 abr | AG58: 20 may | AH58: x | AI58: x | AJ58: x | AK58: x | AL58: x | AM58: x | AN58: x
N59: 1 | Q59: 971 | R59: Keyderson Calle | S59: xm130 | T59: Hammer remo | U59: Negro amarillo | V59: Ansermanuevo | W59: Musculación | Y59: 2100000 | Z59: 2100000 | AA59: 28.610907 | AB59: 0 | AC59: 0 | AD59: 0 | AF59: 46149 | AG59: 20 may | AH59: x | AI59: x | AJ59: x | AK59: x | AL59: x | AM59: x | AN59: x
N60: 1 | Q60: 972 | R60: Keyderson Calle | S60: xm122 | T60: Flexor de pie | U60: Negro amarillo | V60: Ansermanuevo | W60: Musculación | Y60: 2360000 | Z60: 2360000 | AA60: 32.15321 | AB60: 0 | AC60: 0 | AD60: 0 | AF60: 46149 | AG60: 20 may | AH60: x | AI60: x | AJ60: x | AK60: x | AL60: x | AM60: x | AN60: x
N61: 1 | Q61: 973 | R61: Keyderson Calle | S61: xm185 | T61: Sentadilla Hack Up 3.0 Lineal | U61: Negro amarillo | V61: Ansermanuevo | W61: Musculación | Y61: 3990000 | Z61: 3990000 | AA61: 54.360723 | AB61: 0 | AC61: 0 | AD61: 0 | AF61: 46149 | AG61: 20 may | AH61: x | AI61: x | AJ61: x | AK61: x | AL61: x | AM61: x | AN61: x
N62: 1 | Q62: 974 | R62: Keyderson Calle | S62: XA908 | T62: Rack para mancuernas 2 NIVELES | U62: Negro amarillo | V62: Ansermanuevo | W62: Musculación | Y62: 600000 | Z62: 600000 | AA62: 8.1745449 | AB62: 0 | AC62: 0 | AD62: 0 | AF62: 46149 | AG62: 20 may | AH62: x | AI62: x | AJ62: x | AK62: x | AL62: x | AM62: x | AN62: x
AJ74: The Excel should serve more as a database and a reference for you to guide the PRD. I will also give it to Claude Code in its due time, so do not overemphasize the specifics; just understand what it does and how we can replicate it.
